{
"meta":{"test_sets":[],"test_metrics":[],"learn_metrics":[{"best_value":"Min","name":"RMSE"}],"launch_mode":"Train","parameters":"","iteration_count":1000,"learn_sets":["learn"],"name":"experiment"},
"iterations":[
{"learn":[14.59894798],"iteration":0,"passed_time":0.001581191305,"remaining_time":1.579610113},
{"learn":[14.22561675],"iteration":1,"passed_time":0.002570369822,"remaining_time":1.282614541},
{"learn":[13.88706383],"iteration":2,"passed_time":0.003535681229,"remaining_time":1.175024728},
{"learn":[13.52423582],"iteration":3,"passed_time":0.004558946718,"remaining_time":1.135177733},
{"learn":[13.18937652],"iteration":4,"passed_time":0.005316931866,"remaining_time":1.058069441},
{"learn":[12.903859],"iteration":5,"passed_time":0.006108639667,"remaining_time":1.011997971},
{"learn":[12.59227231],"iteration":6,"passed_time":0.006936897908,"remaining_time":0.9840485175},
{"learn":[12.32198669],"iteration":7,"passed_time":0.007817701613,"remaining_time":0.9693950001},
{"learn":[12.05757968],"iteration":8,"passed_time":0.008638397579,"remaining_time":0.9511835557},
{"learn":[11.75768914],"iteration":9,"passed_time":0.009514675934,"remaining_time":0.9419529174},
{"learn":[11.46851343],"iteration":10,"passed_time":0.01033953627,"remaining_time":0.9296183063},
{"learn":[11.23935998],"iteration":11,"passed_time":0.01125572348,"remaining_time":0.9267212331},
{"learn":[11.01953393],"iteration":12,"passed_time":0.01214403273,"remaining_time":0.9220123308},
{"learn":[10.76440142],"iteration":13,"passed_time":0.01329684584,"remaining_time":0.9364778569},
{"learn":[10.53922759],"iteration":14,"passed_time":0.01411228893,"remaining_time":0.9267069729},
{"learn":[10.29741703],"iteration":15,"passed_time":0.01485992962,"remaining_time":0.9138856717},
{"learn":[10.07988635],"iteration":16,"passed_time":0.01558513379,"remaining_time":0.9011874419},
{"learn":[9.86701086],"iteration":17,"passed_time":0.01634898643,"remaining_time":0.8919280374},
{"learn":[9.663229126],"iteration":18,"passed_time":0.01709361467,"remaining_time":0.8825703155},
{"learn":[9.478818556],"iteration":19,"passed_time":0.01785021429,"remaining_time":0.8746605004},
{"learn":[9.310846232],"iteration":20,"passed_time":0.01866214045,"remaining_time":0.8700112141},
{"learn":[9.14365975],"iteration":21,"passed_time":0.01945316244,"remaining_time":0.8647814937},
{"learn":[8.986058219],"iteration":22,"passed_time":0.02026800593,"remaining_time":0.860949643},
{"learn":[8.818191819],"iteration":23,"passed_time":0.0210634448,"remaining_time":0.8565800887},
{"learn":[8.665142781],"iteration":24,"passed_time":0.02183921098,"remaining_time":0.8517292281},
{"learn":[8.530503622],"iteration":25,"passed_time":0.02264266044,"remaining_time":0.848228895},
{"learn":[8.391514766],"iteration":26,"passed_time":0.02349794063,"remaining_time":0.8467961569},
{"learn":[8.28571189],"iteration":27,"passed_time":0.02429622343,"remaining_time":0.8434260419},
{"learn":[8.155247297],"iteration":28,"passed_time":0.0250785824,"remaining_time":0.839700121},
{"learn":[8.034542808],"iteration":29,"passed_time":0.02587724453,"remaining_time":0.8366975733},
{"learn":[7.921554786],"iteration":30,"passed_time":0.02667176955,"remaining_time":0.8337078935},
{"learn":[7.804138483],"iteration":31,"passed_time":0.02744578755,"remaining_time":0.8302350734},
{"learn":[7.693898512],"iteration":32,"passed_time":0.02821845951,"remaining_time":0.8268863741},
{"learn":[7.601352469],"iteration":33,"passed_time":0.02901557481,"remaining_time":0.8243836844},
{"learn":[7.496188442],"iteration":34,"passed_time":0.02981383314,"remaining_time":0.8220099708},
{"learn":[7.399779109],"iteration":35,"passed_time":0.03063149274,"remaining_time":0.8202433055},
{"learn":[7.30623493],"iteration":36,"passed_time":0.03145020747,"remaining_time":0.8185553998},
{"learn":[7.224049092],"iteration":37,"passed_time":0.03227659127,"remaining_time":0.8171073896},
{"learn":[7.141948881],"iteration":38,"passed_time":0.03308225891,"remaining_time":0.8151807901},
{"learn":[7.063209984],"iteration":39,"passed_time":0.03386978733,"remaining_time":0.8128748959},
{"learn":[6.986386006],"iteration":40,"passed_time":0.03465808721,"remaining_time":0.810661113},
{"learn":[6.912264307],"iteration":41,"passed_time":0.03546011277,"remaining_time":0.8088282864},
{"learn":[6.839557377],"iteration":42,"passed_time":0.03623671437,"remaining_time":0.8064775733},
{"learn":[6.775049087],"iteration":43,"passed_time":0.036989653,"remaining_time":0.8036842788},
{"learn":[6.709688799],"iteration":44,"passed_time":0.03779967189,"remaining_time":0.8021930369},
{"learn":[6.651189444],"iteration":45,"passed_time":0.03866949984,"remaining_time":0.8019718011},
{"learn":[6.594199093],"iteration":46,"passed_time":0.03946161646,"remaining_time":0.8001472444},
{"learn":[6.53671767],"iteration":47,"passed_time":0.04023614395,"remaining_time":0.798016855},
{"learn":[6.47776207],"iteration":48,"passed_time":0.04103155891,"remaining_time":0.7963471943},
{"learn":[6.429865768],"iteration":49,"passed_time":0.04182552605,"remaining_time":0.7946849949},
{"learn":[6.385062224],"iteration":50,"passed_time":0.04263956192,"remaining_time":0.7934302796},
{"learn":[6.339237403],"iteration":51,"passed_time":0.04341967712,"remaining_time":0.7915741137},
{"learn":[6.291592269],"iteration":52,"passed_time":0.04419172112,"remaining_time":0.7896143377},
{"learn":[6.245934765],"iteration":53,"passed_time":0.04494330759,"remaining_time":0.7873401662},
{"learn":[6.196112173],"iteration":54,"passed_time":0.04570792447,"remaining_time":0.7853452476},
{"learn":[6.15284626],"iteration":55,"passed_time":0.04646065117,"remaining_time":0.7831938341},
{"learn":[6.111097883],"iteration":56,"passed_time":0.047281514,"remaining_time":0.7822187317},
{"learn":[6.074902138],"iteration":57,"passed_time":0.04808616656,"remaining_time":0.7809856706},
{"learn":[6.042266032],"iteration":58,"passed_time":0.04889828238,"remaining_time":0.7798861647},
{"learn":[6.00935804],"iteration":59,"passed_time":0.04962750129,"remaining_time":0.7774975202},
{"learn":[5.977741769],"iteration":60,"passed_time":0.05038093995,"remaining_time":0.7755361084},
{"learn":[5.945594281],"iteration":61,"passed_time":0.05119713059,"remaining_time":0.7745630402},
{"learn":[5.915542175],"iteration":62,"passed_time":0.05214405192,"remaining_time":0.7755393119},
{"learn":[5.884320188],"iteration":63,"passed_time":0.05300759521,"remaining_time":0.77523608},
{"learn":[5.857662275],"iteration":64,"passed_time":0.05386199826,"remaining_time":0.7747841288},
{"learn":[5.828185436],"iteration":65,"passed_time":0.05477086681,"remaining_time":0.7750907516},
{"learn":[5.802376969],"iteration":66,"passed_time":0.05617625914,"remaining_time":0.7822753698},
{"learn":[5.773966987],"iteration":67,"passed_time":0.05699939744,"remaining_time":0.7812270355},
{"learn":[5.755185058],"iteration":68,"passed_time":0.05783878773,"remaining_time":0.7804045127},
{"learn":[5.728575652],"iteration":69,"passed_time":0.05861328018,"remaining_time":0.7787192938},
{"learn":[5.705500894],"iteration":70,"passed_time":0.05939241144,"remaining_time":0.7771204257},
{"learn":[5.685617736],"iteration":71,"passed_time":0.0601284028,"remaining_time":0.7749883028},
{"learn":[5.666416449],"iteration":72,"passed_time":0.06091195986,"remaining_time":0.7734984491},
{"learn":[5.645681547],"iteration":73,"passed_time":0.06170500034,"remaining_time":0.7721463556},
{"learn":[5.630392845],"iteration":74,"passed_time":0.06247860118,"remaining_time":0.7705694145},
{"learn":[5.612403588],"iteration":75,"passed_time":0.06323523695,"remaining_time":0.7688073545},
{"learn":[5.599354481],"iteration":76,"passed_time":0.06403398808,"remaining_time":0.7675762467},
{"learn":[5.586331617],"iteration":77,"passed_time":0.06487031753,"remaining_time":0.7668004201},
{"learn":[5.573316521],"iteration":78,"passed_time":0.06565845333,"remaining_time":0.7654612091},
{"learn":[5.556862554],"iteration":79,"passed_time":0.06639350915,"remaining_time":0.7635253552},
{"learn":[5.541673002],"iteration":80,"passed_time":0.06715562418,"remaining_time":0.7619261558},
{"learn":[5.530902718],"iteration":81,"passed_time":0.06776420044,"remaining_time":0.7586284879},
{"learn":[5.51458509],"iteration":82,"passed_time":0.06865507717,"remaining_time":0.7585145273},
{"learn":[5.502383806],"iteration":83,"passed_time":0.06950002514,"remaining_time":0.7578812266},
{"learn":[5.485749999],"iteration":84,"passed_time":0.07033452521,"remaining_time":0.7571304772},
{"learn":[5.470591521],"iteration":85,"passed_time":0.07110401173,"remaining_time":0.7556868224},
{"learn":[5.458970723],"iteration":86,"passed_time":0.07197188348,"remaining_time":0.755291145},
{"learn":[5.444926897],"iteration":87,"passed_time":0.07282158541,"remaining_time":0.7546964306},
{"learn":[5.431313512],"iteration":88,"passed_time":0.0736870571,"remaining_time":0.7542574047},
{"learn":[5.417676851],"iteration":89,"passed_time":0.07447006406,"remaining_time":0.7529750921},
{"learn":[5.409687217],"iteration":90,"passed_time":0.07512798088,"remaining_time":0.7504542266},
{"learn":[5.400242706],"iteration":91,"passed_time":0.07592255096,"remaining_time":0.7493225681},
{"learn":[5.388605227],"iteration":92,"passed_time":0.0766341685,"remaining_time":0.7473891487},
{"learn":[5.378980109],"iteration":93,"passed_time":0.07743502212,"remaining_time":0.7463418089},
{"learn":[5.371246091],"iteration":94,"passed_time":0.0782204258,"remaining_time":0.7451524773},
{"learn":[5.362685651],"iteration":95,"passed_time":0.07899029444,"remaining_time":0.7438252726},
{"learn":[5.353517651],"iteration":96,"passed_time":0.07977573094,"remaining_time":0.7426544849},
{"learn":[5.345010748],"iteration":97,"passed_time":0.08054468739,"remaining_time":0.7413398778},
{"learn":[5.338178154],"iteration":98,"passed_time":0.08129270687,"remaining_time":0.7398457463},
{"learn":[5.329766079],"iteration":99,"passed_time":0.08212665962,"remaining_time":0.7391399366},
{"learn":[5.322436584],"iteration":100,"passed_time":0.08293990789,"remaining_time":0.7382472989},
{"learn":[5.312218227],"iteration":101,"passed_time":0.08372691958,"remaining_time":0.7371252332},
{"learn":[5.30099718],"iteration":102,"passed_time":0.08453821777,"remaining_time":0.736221178},
{"learn":[5.291230474],"iteration":103,"passed_time":0.08533800568,"remaining_time":0.7352197412},
{"learn":[5.28221218],"iteration":104,"passed_time":0.0861613609,"remaining_time":0.7344230286},
{"learn":[5.275713444],"iteration":105,"passed_time":0.08690186037,"remaining_time":0.7329270111},
{"learn":[5.26618202],"iteration":106,"passed_time":0.08765950846,"remaining_time":0.7315882341},
{"learn":[5.257596566],"iteration":107,"passed_time":0.08842155563,"remaining_time":0.7302965521},
{"learn":[5.249354525],"iteration":108,"passed_time":0.08924151628,"remaining_time":0.7294879909},
{"learn":[5.239300785],"iteration":109,"passed_time":0.09007982252,"remaining_time":0.7288276549},
{"learn":[5.23643729],"iteration":110,"passed_time":0.09058740992,"remaining_time":0.7255153822},
{"learn":[5.224730829],"iteration":111,"passed_time":0.09139304252,"remaining_time":0.7246162657},
{"learn":[5.216102193],"iteration":112,"passed_time":0.09217563454,"remaining_time":0.7235379455},
{"learn":[5.210692679],"iteration":113,"passed_time":0.0930520475,"remaining_time":0.7231939832},
{"learn":[5.207859123],"iteration":114,"passed_time":0.09383050686,"remaining_time":0.7220869441},
{"learn":[5.202281235],"iteration":115,"passed_time":0.0946520288,"remaining_time":0.7213137367},
{"learn":[5.197497741],"iteration":116,"passed_time":0.09624387659,"remaining_time":0.7263533593},
{"learn":[5.19374791],"iteration":117,"passed_time":0.09707465059,"remaining_time":0.7255918798},
{"learn":[5.189017239],"iteration":118,"passed_time":0.0977158749,"remaining_time":0.723425931},
{"learn":[5.181762718],"iteration":119,"passed_time":0.09850751707,"remaining_time":0.7223884585},
{"learn":[5.175956178],"iteration":120,"passed_time":0.09930419074,"remaining_time":0.7213916005},
{"learn":[5.173050071],"iteration":121,"passed_time":0.1003324455,"remaining_time":0.7220646485},
{"learn":[5.166158378],"iteration":122,"passed_time":0.1011996264,"remaining_time":0.7215615638},
{"learn":[5.160433091],"iteration":123,"passed_time":0.1020175697,"remaining_time":0.7207047663},
{"learn":[5.153328062],"iteration":124,"passed_time":0.1028474732,"remaining_time":0.7199323122},
{"learn":[5.14676388],"iteration":125,"passed_time":0.1036428481,"remaining_time":0.7189194384},
{"learn":[5.14039299],"iteration":126,"passed_time":0.1044766245,"remaining_time":0.7181739623},
{"learn":[5.135510007],"iteration":127,"passed_time":0.1053202921,"remaining_time":0.7174944899},
{"learn":[5.130390495],"iteration":128,"passed_time":0.1063013938,"remaining_time":0.7177404189},
{"learn":[5.12256933],"iteration":129,"passed_time":0.1072755051,"remaining_time":0.717920688},
{"learn":[5.114465262],"iteration":130,"passed_time":0.1080983175,"remaining_time":0.7170796784},
{"learn":[5.109902025],"iteration":131,"passed_time":0.1088940422,"remaining_time":0.7160608231},
{"learn":[5.103991973],"iteration":132,"passed_time":0.109672377,"remaining_time":0.7149319613},
{"learn":[5.094704577],"iteration":133,"passed_time":0.1105099713,"remaining_time":0.7141913069},
{"learn":[5.090882722],"iteration":134,"passed_time":0.1113428072,"remaining_time":0.7134187273},
{"learn":[5.084385661],"iteration":135,"passed_time":0.1125121381,"remaining_time":0.7147829952},
{"learn":[5.080314755],"iteration":136,"passed_time":0.1154696802,"remaining_time":0.7273747008},
{"learn":[5.074448084],"iteration":137,"passed_time":0.1164114098,"remaining_time":0.727149531},
{"learn":[5.069958609],"iteration":138,"passed_time":0.1173745915,"remaining_time":0.7270469301},
{"learn":[5.066394215],"iteration":139,"passed_time":0.1183519266,"remaining_time":0.7270189775},
{"learn":[5.061134494],"iteration":140,"passed_time":0.1191852091,"remaining_time":0.7260999617},
{"learn":[5.058254981],"iteration":141,"passed_time":0.1199504962,"remaining_time":0.724771308},
{"learn":[5.052129175],"iteration":142,"passed_time":0.120754805,"remaining_time":0.7236843909},
{"learn":[5.043359176],"iteration":143,"passed_time":0.1216651214,"remaining_time":0.7232315549},
{"learn":[5.039950858],"iteration":144,"passed_time":0.1224877346,"remaining_time":0.7222552628},
{"learn":[5.035808015],"iteration":145,"passed_time":0.1233044053,"remaining_time":0.7212463158},
{"learn":[5.029521728],"iteration":146,"passed_time":0.1241005505,"remaining_time":0.7201208817},
{"learn":[5.025010948],"iteration":147,"passed_time":0.1248999819,"remaining_time":0.7190188148},
{"learn":[5.02122463],"iteration":148,"passed_time":0.1256850068,"remaining_time":0.7178385289},
{"learn":[5.015270308],"iteration":149,"passed_time":0.1265174789,"remaining_time":0.7169323806},
{"learn":[5.011199518],"iteration":150,"passed_time":0.1273121246,"remaining_time":0.7158145287},
{"learn":[5.004242138],"iteration":151,"passed_time":0.1290168654,"remaining_time":0.7197783016},
{"learn":[5.000625124],"iteration":152,"passed_time":0.1299684194,"remaining_time":0.7194983741},
{"learn":[4.997893895],"iteration":153,"passed_time":0.1310459724,"remaining_time":0.7199019004},
{"learn":[4.994261754],"iteration":154,"passed_time":0.1319846351,"remaining_time":0.7195291397},
{"learn":[4.98800034],"iteration":155,"passed_time":0.1329648469,"remaining_time":0.7193739153},
{"learn":[4.984371519],"iteration":156,"passed_time":0.1337305284,"remaining_time":0.7180562765},
{"learn":[4.978618994],"iteration":157,"passed_time":0.1345199585,"remaining_time":0.7168721838},
{"learn":[4.974242341],"iteration":158,"passed_time":0.1353196935,"remaining_time":0.7157475615},
{"learn":[4.970325368],"iteration":159,"passed_time":0.1361104875,"remaining_time":0.7145800593},
{"learn":[4.966978382],"iteration":160,"passed_time":0.1369732048,"remaining_time":0.7137920424},
{"learn":[4.961587345],"iteration":161,"passed_time":0.1381800713,"remaining_time":0.7147833317},
{"learn":[4.958246651],"iteration":162,"passed_time":0.1391301263,"remaining_time":0.7144289308},
{"learn":[4.955598453],"iteration":163,"passed_time":0.1399124525,"remaining_time":0.7132122577},
{"learn":[4.952080594],"iteration":164,"passed_time":0.1407106691,"remaining_time":0.7120812647},
{"learn":[4.946974019],"iteration":165,"passed_time":0.1414681392,"remaining_time":0.7107495667},
{"learn":[4.941421809],"iteration":166,"passed_time":0.1426801334,"remaining_time":0.7116919227},
{"learn":[4.934938798],"iteration":167,"passed_time":0.1437665224,"remaining_time":0.7119865871},
{"learn":[4.932875027],"iteration":168,"passed_time":0.1446369488,"remaining_time":0.711202985},
{"learn":[4.92861751],"iteration":169,"passed_time":0.1455017525,"remaining_time":0.7103909092},
{"learn":[4.924031965],"iteration":170,"passed_time":0.1462919251,"remaining_time":0.7092164091},
{"learn":[4.922176222],"iteration":171,"passed_time":0.1470898303,"remaining_time":0.7080836016},
{"learn":[4.919068669],"iteration":172,"passed_time":0.1479036292,"remaining_time":0.7070306436},
{"learn":[4.914008019],"iteration":173,"passed_time":0.1487056859,"remaining_time":0.7059246929},
{"learn":[4.910392734],"iteration":174,"passed_time":0.1495814414,"remaining_time":0.7051696524},
{"learn":[4.905671303],"iteration":175,"passed_time":0.1504250511,"remaining_time":0.7042627394},
{"learn":[4.900042499],"iteration":176,"passed_time":0.1512024231,"remaining_time":0.7030485549},
{"learn":[4.896603403],"iteration":177,"passed_time":0.1520427578,"remaining_time":0.702130039},
{"learn":[4.893758675],"iteration":178,"passed_time":0.1528140799,"remaining_time":0.7008958636},
{"learn":[4.88607914],"iteration":179,"passed_time":0.153785301,"remaining_time":0.7005774826},
{"learn":[4.882062149],"iteration":180,"passed_time":0.1546970074,"remaining_time":0.6999825915},
{"learn":[4.877718779],"iteration":181,"passed_time":0.1555277597,"remaining_time":0.6990203706},
{"learn":[4.872106338],"iteration":182,"passed_time":0.1563368875,"remaining_time":0.6979630444},
{"learn":[4.867306715],"iteration":183,"passed_time":0.1578379819,"remaining_time":0.6999771372},
{"learn":[4.860426119],"iteration":184,"passed_time":0.1587592218,"remaining_time":0.6993987338},
{"learn":[4.855017196],"iteration":185,"passed_time":0.1596203845,"remaining_time":0.6985537256},
{"learn":[4.849759737],"iteration":186,"passed_time":0.1604535396,"remaining_time":0.6975867792},
{"learn":[4.846580492],"iteration":187,"passed_time":0.1612698282,"remaining_time":0.6965484067},
{"learn":[4.841351408],"iteration":188,"passed_time":0.1620647414,"remaining_time":0.6954206629},
{"learn":[4.837086961],"iteration":189,"passed_time":0.1628364862,"remaining_time":0.6941976515},
{"learn":[4.832952812],"iteration":190,"passed_time":0.1638744301,"remaining_time":0.6941068794},
{"learn":[4.830574611],"iteration":191,"passed_time":0.1647371413,"remaining_time":0.6932688031},
{"learn":[4.827485271],"iteration":192,"passed_time":0.1654737284,"remaining_time":0.6919031026},
{"learn":[4.823364893],"iteration":193,"passed_time":0.166264776,"remaining_time":0.6907701517},
{"learn":[4.821294877],"iteration":194,"passed_time":0.1670252802,"remaining_time":0.6895146183},
{"learn":[4.818180215],"iteration":195,"passed_time":0.1677985462,"remaining_time":0.6883164854},
{"learn":[4.813183834],"iteration":196,"passed_time":0.168559323,"remaining_time":0.6870717581},
{"learn":[4.808889748],"iteration":197,"passed_time":0.1693698124,"remaining_time":0.6860332807},
{"learn":[4.806482498],"iteration":198,"passed_time":0.1701226532,"remaining_time":0.6847650512},
{"learn":[4.804079535],"iteration":199,"passed_time":0.1709710508,"remaining_time":0.6838842031},
{"learn":[4.800918187],"iteration":200,"passed_time":0.1720651306,"remaining_time":0.6839802951},
{"learn":[4.797680676],"iteration":201,"passed_time":0.1729335429,"remaining_time":0.6831731053},
{"learn":[4.793814693],"iteration":202,"passed_time":0.1738385925,"remaining_time":0.6825091539},
{"learn":[4.791977036],"iteration":203,"passed_time":0.1748796941,"remaining_time":0.6823737084},
{"learn":[4.789279313],"iteration":204,"passed_time":0.1758673325,"remaining_time":0.6820220942},
{"learn":[4.783835696],"iteration":205,"passed_time":0.1768246238,"remaining_time":0.6815473366},
{"learn":[4.779819582],"iteration":206,"passed_time":0.1777264719,"remaining_time":0.6808555179},
{"learn":[4.777873968],"iteration":207,"passed_time":0.1787898548,"remaining_time":0.6807767548},
{"learn":[4.774293192],"iteration":208,"passed_time":0.1797024172,"remaining_time":0.6801177607},
{"learn":[4.76956521],"iteration":209,"passed_time":0.181470925,"remaining_time":0.6826763368},
{"learn":[4.765271961],"iteration":210,"passed_time":0.1825747463,"remaining_time":0.6827084114},
{"learn":[4.757382583],"iteration":211,"passed_time":0.1838509942,"remaining_time":0.6833706766},
{"learn":[4.753117777],"iteration":212,"passed_time":0.1850187722,"remaining_time":0.6836139613},
{"learn":[4.749400835],"iteration":213,"passed_time":0.1863443919,"remaining_time":0.6844237946},
{"learn":[4.746275308],"iteration":214,"passed_time":0.1879890783,"remaining_time":0.6863787277},
{"learn":[4.73976486],"iteration":215,"passed_time":0.189612183,"remaining_time":0.6882219977},
{"learn":[4.736579622],"iteration":216,"passed_time":0.1908689552,"remaining_time":0.6887114835},
{"learn":[4.73556424],"iteration":217,"passed_time":0.1918752139,"remaining_time":0.6882863178},
{"learn":[4.733619932],"iteration":218,"passed_time":0.1927548718,"remaining_time":0.6874043602},
{"learn":[4.730087415],"iteration":219,"passed_time":0.1936235278,"remaining_time":0.6864834168},
{"learn":[4.727273774],"iteration":220,"passed_time":0.1945067166,"remaining_time":0.6856141729},
{"learn":[4.724922337],"iteration":221,"passed_time":0.1954396858,"remaining_time":0.6849192594},
{"learn":[4.722093674],"iteration":222,"passed_time":0.196328984,"remaining_time":0.6840700475},
{"learn":[4.718731175],"iteration":223,"passed_time":0.1971618716,"remaining_time":0.6830250553},
{"learn":[4.715614844],"iteration":224,"passed_time":0.1979446556,"remaining_time":0.6818093692},
{"learn":[4.710461218],"iteration":225,"passed_time":0.1988765602,"remaining_time":0.6811082196},
{"learn":[4.707632714],"iteration":226,"passed_time":0.1997075462,"remaining_time":0.6800613796},
{"learn":[4.705396466],"iteration":227,"passed_time":0.2005728031,"remaining_time":0.6791324738},
{"learn":[4.700452054],"iteration":228,"passed_time":0.2019146442,"remaining_time":0.679808693},
{"learn":[4.699361899],"iteration":229,"passed_time":0.2035336463,"remaining_time":0.6813952508},
{"learn":[4.693313765],"iteration":230,"passed_time":0.2043514072,"remaining_time":0.6802867191},
{"learn":[4.690489483],"iteration":231,"passed_time":0.2052608681,"remaining_time":0.679484253},
{"learn":[4.686787288],"iteration":232,"passed_time":0.206162349,"remaining_time":0.6786545996},
{"learn":[4.684559725],"iteration":233,"passed_time":0.2069738825,"remaining_time":0.6775298888},
{"learn":[4.681387868],"iteration":234,"passed_time":0.2077597907,"remaining_time":0.6763244249},
{"learn":[4.678440679],"iteration":235,"passed_time":0.2084981131,"remaining_time":0.6749684679},
{"learn":[4.674756825],"iteration":236,"passed_time":0.2092309752,"remaining_time":0.6736001438},
{"learn":[4.671836106],"iteration":237,"passed_time":0.2099532031,"remaining_time":0.6722031124},
{"learn":[4.668945527],"iteration":238,"passed_time":0.210726503,"remaining_time":0.6709743464},
{"learn":[4.664825599],"iteration":239,"passed_time":0.2114923274,"remaining_time":0.6697257035},
{"learn":[4.662942724],"iteration":240,"passed_time":0.2122866767,"remaining_time":0.6685709029},
{"learn":[4.657739618],"iteration":241,"passed_time":0.2130778683,"remaining_time":0.6674091908},
{"learn":[4.653125906],"iteration":242,"passed_time":0.2138849243,"remaining_time":0.6662999493},
{"learn":[4.649728602],"iteration":243,"passed_time":0.2146619058,"remaining_time":0.6651000031},
{"learn":[4.649053164],"iteration":244,"passed_time":0.2154469056,"remaining_time":0.6639282194},
{"learn":[4.646737729],"iteration":245,"passed_time":0.2177712028,"remaining_time":0.6674775892},
{"learn":[4.645445677],"iteration":246,"passed_time":0.2190243468,"remaining_time":0.6677138993},
{"learn":[4.641236424],"iteration":247,"passed_time":0.2201557468,"remaining_time":0.6675690387},
{"learn":[4.638346514],"iteration":248,"passed_time":0.2209690802,"remaining_time":0.6664569447},
{"learn":[4.635328086],"iteration":249,"passed_time":0.2218362661,"remaining_time":0.6655087984},
{"learn":[4.632380894],"iteration":250,"passed_time":0.2226719899,"remaining_time":0.664467412},
{"learn":[4.630644328],"iteration":251,"passed_time":0.2234757986,"remaining_time":0.6633329261},
{"learn":[4.626555369],"iteration":252,"passed_time":0.2242310294,"remaining_time":0.6620576244},
{"learn":[4.623551929],"iteration":253,"passed_time":0.2249771133,"remaining_time":0.6607595531},
{"learn":[4.619944395],"iteration":254,"passed_time":0.2257349304,"remaining_time":0.6595000909},
{"learn":[4.61717635],"iteration":255,"passed_time":0.2264984583,"remaining_time":0.6582611443},
{"learn":[4.614882297],"iteration":256,"passed_time":0.2273845883,"remaining_time":0.6573803466},
{"learn":[4.611076648],"iteration":257,"passed_time":0.2282026717,"remaining_time":0.6563038077},
{"learn":[4.608890505],"iteration":258,"passed_time":0.2289528526,"remaining_time":0.6550349953},
{"learn":[4.60646558],"iteration":259,"passed_time":0.2297643527,"remaining_time":0.6539446962},
{"learn":[4.603311372],"iteration":260,"passed_time":0.2306089236,"remaining_time":0.6529501706},
{"learn":[4.600541034],"iteration":261,"passed_time":0.2320581627,"remaining_time":0.6536600156},
{"learn":[4.596882897],"iteration":262,"passed_time":0.2330033876,"remaining_time":0.652941052},
{"learn":[4.596399016],"iteration":263,"passed_time":0.2339506204,"remaining_time":0.6522259721},
{"learn":[4.594441816],"iteration":264,"passed_time":0.2348057071,"remaining_time":0.6512535648},
{"learn":[4.591551684],"iteration":265,"passed_time":0.2355657096,"remaining_time":0.6500196648},
{"learn":[4.587405647],"iteration":266,"passed_time":0.2362916735,"remaining_time":0.6486958678},
{"learn":[4.584967916],"iteration":267,"passed_time":0.2371198456,"remaining_time":0.6476556976},
{"learn":[4.581877324],"iteration":268,"passed_time":0.2379005075,"remaining_time":0.6464879963},
{"learn":[4.577743595],"iteration":269,"passed_time":0.238743254,"remaining_time":0.6454910201},
{"learn":[4.574613408],"iteration":270,"passed_time":0.2395334689,"remaining_time":0.6443538703},
{"learn":[4.57103469],"iteration":271,"passed_time":0.240332091,"remaining_time":0.643241773},
{"learn":[4.563013556],"iteration":272,"passed_time":0.2411571661,"remaining_time":0.6422024166},
{"learn":[4.559054573],"iteration":273,"passed_time":0.2419822122,"remaining_time":0.6411645476},
{"learn":[4.555380074],"iteration":274,"passed_time":0.2427616621,"remaining_time":0.6400080184},
{"learn":[4.552910483],"iteration":275,"passed_time":0.2435152627,"remaining_time":0.6387864136},
{"learn":[4.550049121],"iteration":276,"passed_time":0.2443045659,"remaining_time":0.6376613761},
{"learn":[4.546436513],"iteration":277,"passed_time":0.2450358089,"remaining_time":0.6363879642},
{"learn":[4.544361232],"iteration":278,"passed_time":0.2468630606,"remaining_time":0.6379507767},
{"learn":[4.538798817],"iteration":279,"passed_time":0.2488585551,"remaining_time":0.6399219989},
{"learn":[4.534433062],"iteration":280,"passed_time":0.2496917281,"remaining_time":0.6388909341},
{"learn":[4.531840925],"iteration":281,"passed_time":0.250466695,"remaining_time":0.6377130744},
{"learn":[4.530977306],"iteration":282,"passed_time":0.2511738884,"remaining_time":0.6363663533},
{"learn":[4.527628977],"iteration":283,"passed_time":0.2519279289,"remaining_time":0.6351422432},
{"learn":[4.523525981],"iteration":284,"passed_time":0.2526778228,"remaining_time":0.6339110291},
{"learn":[4.521569245],"iteration":285,"passed_time":0.2533861259,"remaining_time":0.6325793492},
{"learn":[4.516486006],"iteration":286,"passed_time":0.2541045047,"remaining_time":0.6312770449},
{"learn":[4.514714417],"iteration":287,"passed_time":0.2548444202,"remaining_time":0.6300320388},
{"learn":[4.510131693],"iteration":288,"passed_time":0.2556239208,"remaining_time":0.6288879158},
{"learn":[4.507451341],"iteration":289,"passed_time":0.2564418296,"remaining_time":0.6278403413},
{"learn":[4.503106839],"iteration":290,"passed_time":0.2571843559,"remaining_time":0.6266106815},
{"learn":[4.500176578],"iteration":291,"passed_time":0.2579587832,"remaining_time":0.6254617073},
{"learn":[4.495994284],"iteration":292,"passed_time":0.2587015003,"remaining_time":0.6242387739},
{"learn":[4.491272056],"iteration":293,"passed_time":0.2595911083,"remaining_time":0.6233718452},
{"learn":[4.484236178],"iteration":294,"passed_time":0.2609385516,"remaining_time":0.6235989114},
{"learn":[4.48230737],"iteration":295,"passed_time":0.2621867753,"remaining_time":0.6235793575},
{"learn":[4.479525919],"iteration":296,"passed_time":0.2629936705,"remaining_time":0.6225069036},
{"learn":[4.477219084],"iteration":297,"passed_time":0.2636953335,"remaining_time":0.621188336},
{"learn":[4.470068581],"iteration":298,"passed_time":0.264478836,"remaining_time":0.6200657661},
{"learn":[4.466439162],"iteration":299,"passed_time":0.2652959878,"remaining_time":0.6190239716},
{"learn":[4.464125096],"iteration":300,"passed_time":0.2660242339,"remaining_time":0.6177772077},
{"learn":[4.463576236],"iteration":301,"passed_time":0.2667552972,"remaining_time":0.616540389},
{"learn":[4.462221132],"iteration":302,"passed_time":0.2675455155,"remaining_time":0.6154429845},
{"learn":[4.46035449],"iteration":303,"passed_time":0.268310856,"remaining_time":0.614290644},
{"learn":[4.455896924],"iteration":304,"passed_time":0.2690566668,"remaining_time":0.613096339},
{"learn":[4.452969171],"iteration":305,"passed_time":0.2698149767,"remaining_time":0.6119333132},
{"learn":[4.449952456],"iteration":306,"passed_time":0.2705590488,"remaining_time":0.6107407843},
{"learn":[4.446133245],"iteration":307,"passed_time":0.2712884351,"remaining_time":0.6095181724},
{"learn":[4.441551639],"iteration":308,"passed_time":0.272030913,"remaining_time":0.6083280288},
{"learn":[4.437484584],"iteration":309,"passed_time":0.2728076431,"remaining_time":0.6072170121},
{"learn":[4.433098184],"iteration":310,"passed_time":0.2735696208,"remaining_time":0.6060754621},
{"learn":[4.427435741],"iteration":311,"passed_time":0.2743960068,"remaining_time":0.6050783739},
{"learn":[4.426910094],"iteration":312,"passed_time":0.2758800554,"remaining_time":0.6055258725},
{"learn":[4.424637139],"iteration":313,"passed_time":0.2769083625,"remaining_time":0.6049654033},
{"learn":[4.424387869],"iteration":314,"passed_time":0.2777003155,"remaining_time":0.6038879878},
{"learn":[4.422662081],"iteration":315,"passed_time":0.2784506867,"remaining_time":0.6027223724},
{"learn":[4.419757821],"iteration":316,"passed_time":0.2792841561,"remaining_time":0.6017384183},
{"learn":[4.415228913],"iteration":317,"passed_time":0.2800726584,"remaining_time":0.6006589719},
{"learn":[4.41181051],"iteration":318,"passed_time":0.280818725,"remaining_time":0.5994907579},
{"learn":[4.410036907],"iteration":319,"passed_time":0.2815693943,"remaining_time":0.5983349629},
{"learn":[4.408124576],"iteration":320,"passed_time":0.2823223713,"remaining_time":0.5971865736},
{"learn":[4.402650178],"iteration":321,"passed_time":0.283167994,"remaining_time":0.596235714},
{"learn":[4.398346947],"iteration":322,"passed_time":0.2839627765,"remaining_time":0.5951789465},
{"learn":[4.395586306],"iteration":323,"passed_time":0.2847002802,"remaining_time":0.5940042884},
{"learn":[4.392077449],"iteration":324,"passed_time":0.2855509483,"remaining_time":0.5930673542},
{"learn":[4.387356801],"iteration":325,"passed_time":0.2863338435,"remaining_time":0.5919908298},
{"learn":[4.384264465],"iteration":326,"passed_time":0.2871000695,"remaining_time":0.5908817944},
{"learn":[4.382178853],"iteration":327,"passed_time":0.2878726191,"remaining_time":0.5897878049},
{"learn":[4.380090413],"iteration":328,"passed_time":0.2886277013,"remaining_time":0.5886601447},
{"learn":[4.37837933],"iteration":329,"passed_time":0.2896653522,"remaining_time":0.5881084423},
{"learn":[4.377020668],"iteration":330,"passed_time":0.2914081373,"remaining_time":0.5889789845},
{"learn":[4.376635688],"iteration":331,"passed_time":0.2922323096,"remaining_time":0.5879854905},
{"learn":[4.375758049],"iteration":332,"passed_time":0.2931376017,"remaining_time":0.5871554966},
{"learn":[4.371490717],"iteration":333,"passed_time":0.2940688406,"remaining_time":0.58637679},
{"learn":[4.36896543],"iteration":334,"passed_time":0.2949396208,"remaining_time":0.5854771577},
{"learn":[4.364073306],"iteration":335,"passed_time":0.2957722498,"remaining_time":0.5845023031},
{"learn":[4.361955217],"iteration":336,"passed_time":0.2966753749,"remaining_time":0.5836669838},
{"learn":[4.360436867],"iteration":337,"passed_time":0.2975658511,"remaining_time":0.5828064895},
{"learn":[4.355755034],"iteration":338,"passed_time":0.2983880517,"remaining_time":0.5818126907},
{"learn":[4.352723855],"iteration":339,"passed_time":0.2992298081,"remaining_time":0.5808578627},
{"learn":[4.349815941],"iteration":340,"passed_time":0.3000936267,"remaining_time":0.5799463343},
{"learn":[4.344445419],"iteration":341,"passed_time":0.3008650961,"remaining_time":0.5788574072},
{"learn":[4.337738258],"iteration":342,"passed_time":0.3016345465,"remaining_time":0.5777664637},
{"learn":[4.334841727],"iteration":343,"passed_time":0.3024617502,"remaining_time":0.5767875236},
{"learn":[4.32980712],"iteration":344,"passed_time":0.3032434066,"remaining_time":0.5757229894},
{"learn":[4.325419529],"iteration":345,"passed_time":0.3039945821,"remaining_time":0.5746024759},
{"learn":[4.323262256],"iteration":346,"passed_time":0.3055507232,"remaining_time":0.5749989114},
{"learn":[4.317504793],"iteration":347,"passed_time":0.3066103411,"remaining_time":0.5744538575},
{"learn":[4.314807232],"iteration":348,"passed_time":0.3074723431,"remaining_time":0.5735372361},
{"learn":[4.311839163],"iteration":349,"passed_time":0.3082895822,"remaining_time":0.5725377956},
{"learn":[4.310176347],"iteration":350,"passed_time":0.3090211945,"remaining_time":0.5713810691},
{"learn":[4.30864017],"iteration":351,"passed_time":0.3097636997,"remaining_time":0.5702468108},
{"learn":[4.30629414],"iteration":352,"passed_time":0.3105881879,"remaining_time":0.5692650357},
{"learn":[4.305639436],"iteration":353,"passed_time":0.3114312615,"remaining_time":0.5683180647},
{"learn":[4.300605683],"iteration":354,"passed_time":0.3122509335,"remaining_time":0.5673291608},
{"learn":[4.294799549],"iteration":355,"passed_time":0.3130588226,"remaining_time":0.5663198926},
{"learn":[4.291198183],"iteration":356,"passed_time":0.3138519832,"remaining_time":0.5652852247},
{"learn":[4.288942992],"iteration":357,"passed_time":0.3145867576,"remaining_time":0.5641472022},
{"learn":[4.282635598],"iteration":358,"passed_time":0.3153735807,"remaining_time":0.5631043601},
{"learn":[4.279886698],"iteration":359,"passed_time":0.3161626543,"remaining_time":0.562066941},
{"learn":[4.275902234],"iteration":360,"passed_time":0.3170259874,"remaining_time":0.5611623433},
{"learn":[4.270695976],"iteration":361,"passed_time":0.3178390988,"remaining_time":0.5601694614},
{"learn":[4.269147559],"iteration":362,"passed_time":0.3186137926,"remaining_time":0.559110154},
{"learn":[4.26680432],"iteration":363,"passed_time":0.3195316485,"remaining_time":0.5583025506},
{"learn":[4.263923006],"iteration":364,"passed_time":0.3208156778,"remaining_time":0.5581313847},
{"learn":[4.261566364],"iteration":365,"passed_time":0.3216252506,"remaining_time":0.5571322648},
{"learn":[4.258515343],"iteration":366,"passed_time":0.3224561748,"remaining_time":0.5561710045},
{"learn":[4.254846374],"iteration":367,"passed_time":0.3232247747,"remaining_time":0.5551034175},
{"learn":[4.252279079],"iteration":368,"passed_time":0.32408666,"remaining_time":0.5541969714},
{"learn":[4.250929291],"iteration":369,"passed_time":0.3248594026,"remaining_time":0.5531389827},
{"learn":[4.24778192],"iteration":370,"passed_time":0.325711281,"remaining_time":0.5522167001},
{"learn":[4.245940829],"iteration":371,"passed_time":0.3264961496,"remaining_time":0.5511816718},
{"learn":[4.243746476],"iteration":372,"passed_time":0.3273100992,"remaining_time":0.5501968692},
{"learn":[4.241644188],"iteration":373,"passed_time":0.3281581776,"remaining_time":0.5492701047},
{"learn":[4.239943545],"iteration":374,"passed_time":0.3289434416,"remaining_time":0.5482390694},
{"learn":[4.234532034],"iteration":375,"passed_time":0.3297018673,"remaining_time":0.547164801},
{"learn":[4.23130183],"iteration":376,"passed_time":0.3305577454,"remaining_time":0.5462532504},
{"learn":[4.227339206],"iteration":377,"passed_time":0.3313725083,"remaining_time":0.545274339},
{"learn":[4.221410885],"iteration":378,"passed_time":0.3321392187,"remaining_time":0.5442175589},
{"learn":[4.219450553],"iteration":379,"passed_time":0.3329302452,"remaining_time":0.543201979},
{"learn":[4.215880036],"iteration":380,"passed_time":0.3337548396,"remaining_time":0.5422421148},
{"learn":[4.214159284],"iteration":381,"passed_time":0.3348289297,"remaining_time":0.541686593},
{"learn":[4.211490569],"iteration":382,"passed_time":0.3357827603,"remaining_time":0.5409346295},
{"learn":[4.210713455],"iteration":383,"passed_time":0.3365236858,"remaining_time":0.5398400793},
{"learn":[4.206987059],"iteration":384,"passed_time":0.3373278211,"remaining_time":0.5388483376},
{"learn":[4.205940803],"iteration":385,"passed_time":0.3381783651,"remaining_time":0.5379313891},
{"learn":[4.205598197],"iteration":386,"passed_time":0.3388995106,"remaining_time":0.5368098191},
{"learn":[4.204166671],"iteration":387,"passed_time":0.3397194901,"remaining_time":0.5358462061},
{"learn":[4.203225069],"iteration":388,"passed_time":0.3404950233,"remaining_time":0.5348135198},
{"learn":[4.198816768],"iteration":389,"passed_time":0.3413133442,"remaining_time":0.5338490768},
{"learn":[4.194109661],"iteration":390,"passed_time":0.3420584235,"remaining_time":0.5327713042},
{"learn":[4.191033475],"iteration":391,"passed_time":0.3428505135,"remaining_time":0.5317681433},
{"learn":[4.189495416],"iteration":392,"passed_time":0.344285275,"remaining_time":0.5317586817},
{"learn":[4.187073751],"iteration":393,"passed_time":0.3451270247,"remaining_time":0.5308298908},
{"learn":[4.186094754],"iteration":394,"passed_time":0.3460540036,"remaining_time":0.5300320814},
{"learn":[4.185720175],"iteration":395,"passed_time":0.34686056,"remaining_time":0.5290499451},
{"learn":[4.183118744],"iteration":396,"passed_time":0.3476569901,"remaining_time":0.5280533124},
{"learn":[4.179708108],"iteration":397,"passed_time":0.3487855373,"remaining_time":0.5275600338},
{"learn":[4.178141198],"iteration":398,"passed_time":0.3504492662,"remaining_time":0.5278696967},
{"learn":[4.175594376],"iteration":399,"passed_time":0.3517266099,"remaining_time":0.5275899148},
{"learn":[4.174946783],"iteration":400,"passed_time":0.352869128,"remaining_time":0.5271037598},
{"learn":[4.168454832],"iteration":401,"passed_time":0.3536620195,"remaining_time":0.5260942479},
{"learn":[4.165286814],"iteration":402,"passed_time":0.3544744885,"remaining_time":0.525114813},
{"learn":[4.163425433],"iteration":403,"passed_time":0.3552284633,"remaining_time":0.5240499112},
{"learn":[4.161595062],"iteration":404,"passed_time":0.3560133486,"remaining_time":0.5230319566},
{"learn":[4.159282638],"iteration":405,"passed_time":0.356778163,"remaining_time":0.5219857852},
{"learn":[4.156000256],"iteration":406,"passed_time":0.3575331623,"remaining_time":0.520926696},
{"learn":[4.152991992],"iteration":407,"passed_time":0.3583613889,"remaining_time":0.5199753486},
{"learn":[4.15054018],"iteration":408,"passed_time":0.3592194969,"remaining_time":0.5190677815},
{"learn":[4.148798611],"iteration":409,"passed_time":0.3600591758,"remaining_time":0.518133936},
{"learn":[4.145416212],"iteration":410,"passed_time":0.3609475401,"remaining_time":0.5172703191},
{"learn":[4.142162981],"iteration":411,"passed_time":0.361697048,"remaining_time":0.5162084084},
{"learn":[4.138663791],"iteration":412,"passed_time":0.3625385419,"remaining_time":0.5152787509},
{"learn":[4.138439056],"iteration":413,"passed_time":0.3634691796,"remaining_time":0.5144756986},
{"learn":[4.134148532],"iteration":414,"passed_time":0.3652804374,"remaining_time":0.5149133876},
{"learn":[4.131763412],"iteration":415,"passed_time":0.3661577614,"remaining_time":0.514029165},
{"learn":[4.130482697],"iteration":416,"passed_time":0.3669513876,"remaining_time":0.5130279591},
{"learn":[4.126577901],"iteration":417,"passed_time":0.3677611556,"remaining_time":0.5120502215},
{"learn":[4.123799959],"iteration":418,"passed_time":0.3685342064,"remaining_time":0.5110223721},
{"learn":[4.122099571],"iteration":419,"passed_time":0.3692789531,"remaining_time":0.5099566495},
{"learn":[4.120031125],"iteration":420,"passed_time":0.370038519,"remaining_time":0.5089128325},
{"learn":[4.117561888],"iteration":421,"passed_time":0.3708431382,"remaining_time":0.5079320707},
{"learn":[4.113878276],"iteration":422,"passed_time":0.3716401606,"remaining_time":0.5069417793},
{"learn":[4.112292572],"iteration":423,"passed_time":0.3724362619,"remaining_time":0.5059511482},
{"learn":[4.109322704],"iteration":424,"passed_time":0.3732107026,"remaining_time":0.5049321271},
{"learn":[4.108860839],"iteration":425,"passed_time":0.3739238086,"remaining_time":0.5038316106},
{"learn":[4.10676474],"iteration":426,"passed_time":0.374765139,"remaining_time":0.5029049757},
{"learn":[4.104099933],"iteration":427,"passed_time":0.3755445606,"remaining_time":0.5018960015},
{"learn":[4.101067508],"iteration":428,"passed_time":0.3763735647,"remaining_time":0.5009540919},
{"learn":[4.099791928],"iteration":429,"passed_time":0.3771097585,"remaining_time":0.4998896799},
{"learn":[4.09925354],"iteration":430,"passed_time":0.3779379406,"remaining_time":0.4989482324},
{"learn":[4.097633015],"iteration":431,"passed_time":0.380725941,"remaining_time":0.5005841077},
{"learn":[4.093046434],"iteration":432,"passed_time":0.381708331,"remaining_time":0.4998351586},
{"learn":[4.089477079],"iteration":433,"passed_time":0.3825157301,"remaining_time":0.4988569199},
{"learn":[4.087709129],"iteration":434,"passed_time":0.3832563175,"remaining_time":0.4977926882},
{"learn":[4.085057133],"iteration":435,"passed_time":0.3839691297,"remaining_time":0.4966940119},
{"learn":[4.083240979],"iteration":436,"passed_time":0.3846997459,"remaining_time":0.4956200387},
{"learn":[4.081320109],"iteration":437,"passed_time":0.3854966965,"remaining_time":0.4946327476},
{"learn":[4.077826864],"iteration":438,"passed_time":0.3862621494,"remaining_time":0.4936060725},
{"learn":[4.077402319],"iteration":439,"passed_time":0.3870196723,"remaining_time":0.4925704921},
{"learn":[4.074127047],"iteration":440,"passed_time":0.3878346354,"remaining_time":0.4916089823},
{"learn":[4.073605414],"iteration":441,"passed_time":0.3885610115,"remaining_time":0.4905362996},
{"learn":[4.069017079],"iteration":442,"passed_time":0.3893143061,"remaining_time":0.489499026},
{"learn":[4.06303955],"iteration":443,"passed_time":0.3900442364,"remaining_time":0.4884337736},
{"learn":[4.062265407],"iteration":444,"passed_time":0.3907776909,"remaining_time":0.4873744235},
{"learn":[4.062016259],"iteration":445,"passed_time":0.3915098705,"remaining_time":0.4863149513},
{"learn":[4.058817905],"iteration":446,"passed_time":0.3923018781,"remaining_time":0.4853309589},
{"learn":[4.05817717],"iteration":447,"passed_time":0.3931509582,"remaining_time":0.484418145},
{"learn":[4.0563594],"iteration":448,"passed_time":0.39559234,"remaining_time":0.4854596422},
{"learn":[4.054350875],"iteration":449,"passed_time":0.3965147323,"remaining_time":0.4846291173},
{"learn":[4.051418966],"iteration":450,"passed_time":0.3973720048,"remaining_time":0.483718915},
{"learn":[4.051073315],"iteration":451,"passed_time":0.3981622932,"remaining_time":0.482727736},
{"learn":[4.049566411],"iteration":452,"passed_time":0.3989947809,"remaining_time":0.4817883999},
{"learn":[4.04675657],"iteration":453,"passed_time":0.3998397789,"remaining_time":0.4808645799},
{"learn":[4.044573835],"iteration":454,"passed_time":0.4006165107,"remaining_time":0.479859337},
{"learn":[4.043479099],"iteration":455,"passed_time":0.401455832,"remaining_time":0.4789297645},
{"learn":[4.042043723],"iteration":456,"passed_time":0.4022499521,"remaining_time":0.4779468796},
{"learn":[4.039274088],"iteration":457,"passed_time":0.4030363887,"remaining_time":0.4769557263},
{"learn":[4.033508811],"iteration":458,"passed_time":0.4038006562,"remaining_time":0.4759393356},
{"learn":[4.031119943],"iteration":459,"passed_time":0.4045781328,"remaining_time":0.4749395472},
{"learn":[4.029180569],"iteration":460,"passed_time":0.4053446258,"remaining_time":0.4739278813},
{"learn":[4.02533684],"iteration":461,"passed_time":0.4061010518,"remaining_time":0.4729055539},
{"learn":[4.02014698],"iteration":462,"passed_time":0.4068493884,"remaining_time":0.4718749925},
{"learn":[4.014217135],"iteration":463,"passed_time":0.4077688411,"remaining_time":0.4710433164},
{"learn":[4.011613137],"iteration":464,"passed_time":0.4093321785,"remaining_time":0.4709520763},
{"learn":[4.010043556],"iteration":465,"passed_time":0.4101669344,"remaining_time":0.4700196201},
{"learn":[4.007318457],"iteration":466,"passed_time":0.4109447102,"remaining_time":0.4690225493},
{"learn":[4.00501934],"iteration":467,"passed_time":0.4117768364,"remaining_time":0.4680881986},
{"learn":[4.004729803],"iteration":468,"passed_time":0.4125025228,"remaining_time":0.4670337731},
{"learn":[4.004336033],"iteration":469,"passed_time":0.4132886879,"remaining_time":0.4660489459},
{"learn":[4.002121142],"iteration":470,"passed_time":0.4141836049,"remaining_time":0.4651871062},
{"learn":[4.000544015],"iteration":471,"passed_time":0.4150406317,"remaining_time":0.4642827405},
{"learn":[4.000223111],"iteration":472,"passed_time":0.4158232787,"remaining_time":0.4632957038},
{"learn":[3.997105999],"iteration":473,"passed_time":0.4166335274,"remaining_time":0.462340159},
{"learn":[3.995219326],"iteration":474,"passed_time":0.4173741281,"remaining_time":0.4613082468},
{"learn":[3.994804516],"iteration":475,"passed_time":0.4180907882,"remaining_time":0.4602512038},
{"learn":[3.99444034],"iteration":476,"passed_time":0.4188380412,"remaining_time":0.4592291312},
{"learn":[3.99033871],"iteration":477,"passed_time":0.4196455144,"remaining_time":0.4582739717},
{"learn":[3.988595084],"iteration":478,"passed_time":0.4203857068,"remaining_time":0.4572462489},
{"learn":[3.987644537],"iteration":479,"passed_time":0.4211031868,"remaining_time":0.4561951191},
{"learn":[3.987170087],"iteration":480,"passed_time":0.4218289989,"remaining_time":0.4551543668},
{"learn":[3.986522123],"iteration":481,"passed_time":0.4227168187,"remaining_time":0.4542890292},
{"learn":[3.986067041],"iteration":482,"passed_time":0.4243262996,"remaining_time":0.4541960598},
{"learn":[3.985633964],"iteration":483,"passed_time":0.4251620795,"remaining_time":0.453271969},
{"learn":[3.984795519],"iteration":484,"passed_time":0.4259250177,"remaining_time":0.4522708951},
{"learn":[3.984215833],"iteration":485,"passed_time":0.4267493502,"remaining_time":0.4513357325},
{"learn":[3.982358316],"iteration":486,"passed_time":0.427489101,"remaining_time":0.4503119278},
{"learn":[3.977750793],"iteration":487,"passed_time":0.4284038271,"remaining_time":0.4494728677},
{"learn":[3.974878608],"iteration":488,"passed_time":0.4291519261,"remaining_time":0.4484593747},
{"learn":[3.973035965],"iteration":489,"passed_time":0.4299195398,"remaining_time":0.4474672761},
{"learn":[3.970272655],"iteration":490,"passed_time":0.430684892,"remaining_time":0.4464737475},
{"learn":[3.965238471],"iteration":491,"passed_time":0.431463496,"remaining_time":0.4454948292},
{"learn":[3.964092711],"iteration":492,"passed_time":0.4322215184,"remaining_time":0.4444955575},
{"learn":[3.963949046],"iteration":493,"passed_time":0.4330088538,"remaining_time":0.4435272875},
{"learn":[3.962984243],"iteration":494,"passed_time":0.433842425,"remaining_time":0.4426069184},
{"learn":[3.959805302],"iteration":495,"passed_time":0.4346376842,"remaining_time":0.4416479695},
{"learn":[3.95905386],"iteration":496,"passed_time":0.435390837,"remaining_time":0.4406470644},
{"learn":[3.956023362],"iteration":497,"passed_time":0.4362200191,"remaining_time":0.4397237944},
{"learn":[3.951988081],"iteration":498,"passed_time":0.4370023653,"remaining_time":0.4387538778},
{"learn":[3.950487405],"iteration":499,"passed_time":0.4384481437,"remaining_time":0.4384481437},
{"learn":[3.947431882],"iteration":500,"passed_time":0.4398408455,"remaining_time":0.4380849938},
{"learn":[3.946117041],"iteration":501,"passed_time":0.4405721162,"remaining_time":0.4370615814},
{"learn":[3.941456597],"iteration":502,"passed_time":0.4414030877,"remaining_time":0.4361378421},
{"learn":[3.941050588],"iteration":503,"passed_time":0.4423756388,"remaining_time":0.4353538032},
{"learn":[3.936332767],"iteration":504,"passed_time":0.443304833,"remaining_time":0.4345265195},
{"learn":[3.935942094],"iteration":505,"passed_time":0.444198092,"remaining_time":0.4336637499},
{"learn":[3.935307263],"iteration":506,"passed_time":0.4450331444,"remaining_time":0.4327442607},
{"learn":[3.934648742],"iteration":507,"passed_time":0.4458771579,"remaining_time":0.4318337829},
{"learn":[3.931621657],"iteration":508,"passed_time":0.4466692362,"remaining_time":0.4308734675},
{"learn":[3.926612059],"iteration":509,"passed_time":0.4474347919,"remaining_time":0.4298883295},
{"learn":[3.923390835],"iteration":510,"passed_time":0.4482131851,"remaining_time":0.4289163357},
{"learn":[3.918383458],"iteration":511,"passed_time":0.4489117444,"remaining_time":0.4278690064},
{"learn":[3.916730849],"iteration":512,"passed_time":0.4496984752,"remaining_time":0.4269067397},
{"learn":[3.913545154],"iteration":513,"passed_time":0.4506809631,"remaining_time":0.4261302491},
{"learn":[3.911249406],"iteration":514,"passed_time":0.4520282739,"remaining_time":0.4256965298},
{"learn":[3.911064439],"iteration":515,"passed_time":0.4537264881,"remaining_time":0.4255884113},
{"learn":[3.908052479],"iteration":516,"passed_time":0.4546257291,"remaining_time":0.4247277121},
{"learn":[3.902549199],"iteration":517,"passed_time":0.4553549719,"remaining_time":0.4237086805},
{"learn":[3.901273551],"iteration":518,"passed_time":0.4560716816,"remaining_time":0.42267915},
{"learn":[3.901036018],"iteration":519,"passed_time":0.4567901067,"remaining_time":0.4216524062},
{"learn":[3.898943587],"iteration":520,"passed_time":0.4577990613,"remaining_time":0.4208939547},
{"learn":[3.896947202],"iteration":521,"passed_time":0.4586282079,"remaining_time":0.4199698915},
{"learn":[3.895891758],"iteration":522,"passed_time":0.459455372,"remaining_time":0.4190443833},
{"learn":[3.894614243],"iteration":523,"passed_time":0.4602435256,"remaining_time":0.4180838134},
{"learn":[3.893103843],"iteration":524,"passed_time":0.4610029224,"remaining_time":0.4170978822},
{"learn":[3.889084704],"iteration":525,"passed_time":0.4618175407,"remaining_time":0.4161625747},
{"learn":[3.886875972],"iteration":526,"passed_time":0.4626018202,"remaining_time":0.4152004952},
{"learn":[3.884836055],"iteration":527,"passed_time":0.463399969,"remaining_time":0.4142514874},
{"learn":[3.884258279],"iteration":528,"passed_time":0.4641501227,"remaining_time":0.4132603171},
{"learn":[3.882553104],"iteration":529,"passed_time":0.4651004591,"remaining_time":0.412447577},
{"learn":[3.881659772],"iteration":530,"passed_time":0.4661099283,"remaining_time":0.4116865468},
{"learn":[3.88001276],"iteration":531,"passed_time":0.4668831036,"remaining_time":0.4107167152},
{"learn":[3.877989798],"iteration":532,"passed_time":0.4676171978,"remaining_time":0.4097133797},
{"learn":[3.874663922],"iteration":533,"passed_time":0.4683470102,"remaining_time":0.408707316},
{"learn":[3.873427541],"iteration":534,"passed_time":0.4690887806,"remaining_time":0.4077126784},
{"learn":[3.869501676],"iteration":535,"passed_time":0.4698558337,"remaining_time":0.4067408709},
{"learn":[3.867213538],"iteration":536,"passed_time":0.470601249,"remaining_time":0.40575117},
{"learn":[3.865509489],"iteration":537,"passed_time":0.4713355305,"remaining_time":0.4047528162},
{"learn":[3.860567505],"iteration":538,"passed_time":0.4720573401,"remaining_time":0.4037447751},
{"learn":[3.860108807],"iteration":539,"passed_time":0.4727833569,"remaining_time":0.4027413781},
{"learn":[3.858657968],"iteration":540,"passed_time":0.4735552974,"remaining_time":0.4017779696},
{"learn":[3.858063632],"iteration":541,"passed_time":0.4743331249,"remaining_time":0.4008202421},
{"learn":[3.85667526],"iteration":542,"passed_time":0.4750612481,"remaining_time":0.3998213451},
{"learn":[3.856359544],"iteration":543,"passed_time":0.4778043689,"remaining_time":0.4005124857},
{"learn":[3.854613023],"iteration":544,"passed_time":0.4787484724,"remaining_time":0.3996890917},
{"learn":[3.852750347],"iteration":545,"passed_time":0.4795154849,"remaining_time":0.3987180039},
{"learn":[3.85151813],"iteration":546,"passed_time":0.4802662265,"remaining_time":0.3977341876},
{"learn":[3.848570203],"iteration":547,"passed_time":0.4810014659,"remaining_time":0.3967384353},
{"learn":[3.846959358],"iteration":548,"passed_time":0.4817733719,"remaining_time":0.3957737536},
{"learn":[3.843532616],"iteration":549,"passed_time":0.4825242448,"remaining_time":0.3947925639},
{"learn":[3.840904585],"iteration":550,"passed_time":0.4833448345,"remaining_time":0.3938690212},
{"learn":[3.834740738],"iteration":551,"passed_time":0.4841133805,"remaining_time":0.3929036131},
{"learn":[3.834482997],"iteration":552,"passed_time":0.4848663914,"remaining_time":0.3919263598},
{"learn":[3.832791637],"iteration":553,"passed_time":0.4856465594,"remaining_time":0.3909717789},
{"learn":[3.830452156],"iteration":554,"passed_time":0.4864168035,"remaining_time":0.3900098695},
{"learn":[3.827062994],"iteration":555,"passed_time":0.4872338407,"remaining_time":0.3890860167},
{"learn":[3.824849146],"iteration":556,"passed_time":0.4880391646,"remaining_time":0.3881532315},
{"learn":[3.82288745],"iteration":557,"passed_time":0.4888993623,"remaining_time":0.3872643694},
{"learn":[3.818642717],"iteration":558,"passed_time":0.4896964198,"remaining_time":0.3863257981},
{"learn":[3.816098571],"iteration":559,"passed_time":0.4915532603,"remaining_time":0.3862204188},
{"learn":[3.812301313],"iteration":560,"passed_time":0.492928329,"remaining_time":0.385731794},
{"learn":[3.812034516],"iteration":561,"passed_time":0.4936773769,"remaining_time":0.3847521194},
{"learn":[3.809944106],"iteration":562,"passed_time":0.4944567129,"remaining_time":0.3837967736},
{"learn":[3.808164415],"iteration":563,"passed_time":0.4952057202,"remaining_time":0.3828186064},
{"learn":[3.807932927],"iteration":564,"passed_time":0.4959663151,"remaining_time":0.3818501718},
{"learn":[3.804475824],"iteration":565,"passed_time":0.4967032109,"remaining_time":0.3808642995},
{"learn":[3.804146668],"iteration":566,"passed_time":0.497439888,"remaining_time":0.3798791385},
{"learn":[3.802708358],"iteration":567,"passed_time":0.4982819431,"remaining_time":0.378974999},
{"learn":[3.799231885],"iteration":568,"passed_time":0.4990793761,"remaining_time":0.3780372778},
{"learn":[3.796794833],"iteration":569,"passed_time":0.4998345918,"remaining_time":0.3770682008},
{"learn":[3.793697842],"iteration":570,"passed_time":0.500652643,"remaining_time":0.376147082},
{"learn":[3.793458053],"iteration":571,"passed_time":0.5014242776,"remaining_time":0.3751915923},
{"learn":[3.792086704],"iteration":572,"passed_time":0.5022225743,"remaining_time":0.374256613},
{"learn":[3.790638244],"iteration":573,"passed_time":0.5029813387,"remaining_time":0.3732927705},
{"learn":[3.787445237],"iteration":574,"passed_time":0.5037469601,"remaining_time":0.3723347097},
{"learn":[3.785660817],"iteration":575,"passed_time":0.5045642404,"remaining_time":0.3714153436},
{"learn":[3.783749179],"iteration":576,"passed_time":0.5062535406,"remaining_time":0.3711356112},
{"learn":[3.782529668],"iteration":577,"passed_time":0.5071234225,"remaining_time":0.370252741},
{"learn":[3.778251213],"iteration":578,"passed_time":0.5078997099,"remaining_time":0.3693018616},
{"learn":[3.776293015],"iteration":579,"passed_time":0.5086637894,"remaining_time":0.3683427441},
{"learn":[3.774310878],"iteration":580,"passed_time":0.5094194552,"remaining_time":0.3673782302},
{"learn":[3.772299779],"iteration":581,"passed_time":0.5101637252,"remaining_time":0.3664062494},
{"learn":[3.770846818],"iteration":582,"passed_time":0.5109048694,"remaining_time":0.3654328139},
{"learn":[3.770146794],"iteration":583,"passed_time":0.5117359137,"remaining_time":0.3645242125},
{"learn":[3.768585925],"iteration":584,"passed_time":0.5125362678,"remaining_time":0.3635941045},
{"learn":[3.767977095],"iteration":585,"passed_time":0.5133354506,"remaining_time":0.3626636118},
{"learn":[3.765246591],"iteration":586,"passed_time":0.5140888447,"remaining_time":0.3617013507},
{"learn":[3.762675013],"iteration":587,"passed_time":0.5148809864,"remaining_time":0.3607669496},
{"learn":[3.75986927],"iteration":588,"passed_time":0.5156993023,"remaining_time":0.3598512958},
{"learn":[3.759643515],"iteration":589,"passed_time":0.5164702022,"remaining_time":0.3589030218},
{"learn":[3.755977924],"iteration":590,"passed_time":0.5172942415,"remaining_time":0.3579921231},
{"learn":[3.753515599],"iteration":591,"passed_time":0.518087,"remaining_time":0.3570599595},
{"learn":[3.752534797],"iteration":592,"passed_time":0.518853404,"remaining_time":0.3561101778},
{"learn":[3.75102903],"iteration":593,"passed_time":0.5197415914,"remaining_time":0.3552442527},
{"learn":[3.749546887],"iteration":594,"passed_time":0.5211632002,"remaining_time":0.3547413379},
{"learn":[3.749439256],"iteration":595,"passed_time":0.5219821385,"remaining_time":0.3538268187},
{"learn":[3.746975689],"iteration":596,"passed_time":0.5227404223,"remaining_time":0.3528716754},
{"learn":[3.745832467],"iteration":597,"passed_time":0.5235483554,"remaining_time":0.3519505667},
{"learn":[3.740349398],"iteration":598,"passed_time":0.5242905497,"remaining_time":0.3509858271},
{"learn":[3.738780336],"iteration":599,"passed_time":0.5250220035,"remaining_time":0.350014669},
{"learn":[3.738302984],"iteration":600,"passed_time":0.5257716643,"remaining_time":0.3490563961},
{"learn":[3.736138802],"iteration":601,"passed_time":0.5265521099,"remaining_time":0.348119169},
{"learn":[3.735506691],"iteration":602,"passed_time":0.5273307751,"remaining_time":0.3471812897},
{"learn":[3.731145593],"iteration":603,"passed_time":0.5280915925,"remaining_time":0.3462322361},
{"learn":[3.728587979],"iteration":604,"passed_time":0.5288576989,"remaining_time":0.3452872579},
{"learn":[3.727727594],"iteration":605,"passed_time":0.5296623714,"remaining_time":0.3443679445},
{"learn":[3.72399577],"iteration":606,"passed_time":0.5304287838,"remaining_time":0.3434242373},
{"learn":[3.722876617],"iteration":607,"passed_time":0.5312205767,"remaining_time":0.3424974771},
{"learn":[3.72157938],"iteration":608,"passed_time":0.5319762402,"remaining_time":0.3415479637},
{"learn":[3.72029921],"iteration":609,"passed_time":0.53305622,"remaining_time":0.3408064357},
{"learn":[3.717136691],"iteration":610,"passed_time":0.5338920093,"remaining_time":0.3399083333},
{"learn":[3.715190748],"iteration":611,"passed_time":0.5351417788,"remaining_time":0.3392728924},
{"learn":[3.712122118],"iteration":612,"passed_time":0.5360718096,"remaining_time":0.3384335894},
{"learn":[3.707768851],"iteration":613,"passed_time":0.5368694861,"remaining_time":0.3375107844},
{"learn":[3.704289789],"iteration":614,"passed_time":0.5376337603,"remaining_time":0.336567476},
{"learn":[3.703825972],"iteration":615,"passed_time":0.5384046001,"remaining_time":0.3356288416},
{"learn":[3.702743061],"iteration":616,"passed_time":0.5392020197,"remaining_time":0.3347072505},
{"learn":[3.698646854],"iteration":617,"passed_time":0.5399596494,"remaining_time":0.3337614661},
{"learn":[3.696267258],"iteration":618,"passed_time":0.5407610426,"remaining_time":0.3328432265},
{"learn":[3.694034646],"iteration":619,"passed_time":0.5415460508,"remaining_time":0.3319153214},
{"learn":[3.691484756],"iteration":620,"passed_time":0.5423481275,"remaining_time":0.3309982936},
{"learn":[3.689150283],"iteration":621,"passed_time":0.5431073396,"remaining_time":0.3300555858},
{"learn":[3.68687633],"iteration":622,"passed_time":0.5438762093,"remaining_time":0.3291193113},
{"learn":[3.685550978],"iteration":623,"passed_time":0.5447166286,"remaining_time":0.3282266865},
{"learn":[3.68461737],"iteration":624,"passed_time":0.5455197054,"remaining_time":0.3273118233},
{"learn":[3.683815104],"iteration":625,"passed_time":0.5464040188,"remaining_time":0.3264458515},
{"learn":[3.680916776],"iteration":626,"passed_time":0.547247415,"remaining_time":0.3255554797},
{"learn":[3.679643679],"iteration":627,"passed_time":0.548030665,"remaining_time":0.3246296296},
{"learn":[3.679008696],"iteration":628,"passed_time":0.54880168,"remaining_time":0.3236970163},
{"learn":[3.676220615],"iteration":629,"passed_time":0.549821982,"remaining_time":0.3229113227},
{"learn":[3.676030586],"iteration":630,"passed_time":0.5506710715,"remaining_time":0.3220247629},
{"learn":[3.675588632],"iteration":631,"passed_time":0.5514192278,"remaining_time":0.3210795504},
{"learn":[3.673730068],"iteration":632,"passed_time":0.5522210326,"remaining_time":0.3201660647},
{"learn":[3.672419811],"iteration":633,"passed_time":0.5529995759,"remaining_time":0.3192395028},
{"learn":[3.670396298],"iteration":634,"passed_time":0.553832483,"remaining_time":0.3183446556},
{"learn":[3.66951727],"iteration":635,"passed_time":0.554689834,"remaining_time":0.317463993},
{"learn":[3.667609355],"iteration":636,"passed_time":0.5554602177,"remaining_time":0.3165338446},
{"learn":[3.667169612],"iteration":637,"passed_time":0.5562386948,"remaining_time":0.3156087892},
{"learn":[3.664644921],"iteration":638,"passed_time":0.5570375144,"remaining_time":0.3146956849},
{"learn":[3.664062112],"iteration":639,"passed_time":0.5578198305,"remaining_time":0.3137736547},
{"learn":[3.662184344],"iteration":640,"passed_time":0.5585748877,"remaining_time":0.3128367936},
{"learn":[3.66045633],"iteration":641,"passed_time":0.5593604844,"remaining_time":0.3119175287},
{"learn":[3.658454251],"iteration":642,"passed_time":0.5601650914,"remaining_time":0.3110092342},
{"learn":[3.658297037],"iteration":643,"passed_time":0.5609376727,"remaining_time":0.3100835582},
{"learn":[3.654329933],"iteration":644,"passed_time":0.5617981101,"remaining_time":0.3092067117},
{"learn":[3.653317956],"iteration":645,"passed_time":0.5626475311,"remaining_time":0.3083238793},
{"learn":[3.65100043],"iteration":646,"passed_time":0.5634154942,"remaining_time":0.307396707},
{"learn":[3.650511247],"iteration":647,"passed_time":0.5645743989,"remaining_time":0.3066823895},
{"learn":[3.649836647],"iteration":648,"passed_time":0.5656358896,"remaining_time":0.3059140173},
{"learn":[3.649562465],"iteration":649,"passed_time":0.5664245182,"remaining_time":0.3049978175},
{"learn":[3.64805855],"iteration":650,"passed_time":0.5673305195,"remaining_time":0.3041449329},
{"learn":[3.646433857],"iteration":651,"passed_time":0.5680781974,"remaining_time":0.3032073815},
{"learn":[3.644704196],"iteration":652,"passed_time":0.5689140207,"remaining_time":0.3023172515},
{"learn":[3.643569962],"iteration":653,"passed_time":0.5700167279,"remaining_time":0.301568483},
{"learn":[3.641942806],"iteration":654,"passed_time":0.5710521606,"remaining_time":0.3007831991},
{"learn":[3.641821696],"iteration":655,"passed_time":0.5721853372,"remaining_time":0.3000484085},
{"learn":[3.640934089],"iteration":656,"passed_time":0.5729928019,"remaining_time":0.2991423608},
{"learn":[3.639544036],"iteration":657,"passed_time":0.5737089454,"remaining_time":0.2981891479},
{"learn":[3.638748407],"iteration":658,"passed_time":0.5744410093,"remaining_time":0.2972448925},
{"learn":[3.637997537],"iteration":659,"passed_time":0.575261994,"remaining_time":0.2963470878},
{"learn":[3.635967284],"iteration":660,"passed_time":0.5764568518,"remaining_time":0.2956412598},
{"learn":[3.634213089],"iteration":661,"passed_time":0.5772645118,"remaining_time":0.2947362613},
{"learn":[3.632915457],"iteration":662,"passed_time":0.5780561156,"remaining_time":0.2938233951},
{"learn":[3.629071048],"iteration":663,"passed_time":0.5794350755,"remaining_time":0.2932081105},
{"learn":[3.627421148],"iteration":664,"passed_time":0.5803779699,"remaining_time":0.292370857},
{"learn":[3.62684485],"iteration":665,"passed_time":0.5812565893,"remaining_time":0.2915010523},
{"learn":[3.626514097],"iteration":666,"passed_time":0.5820660581,"remaining_time":0.2905966977},
{"learn":[3.624267502],"iteration":667,"passed_time":0.5828898461,"remaining_time":0.2896997439},
{"learn":[3.621273835],"iteration":668,"passed_time":0.5837008623,"remaining_time":0.2887966897},
{"learn":[3.621024042],"iteration":669,"passed_time":0.5845235512,"remaining_time":0.2878996595},
{"learn":[3.619427172],"iteration":670,"passed_time":0.5852882615,"remaining_time":0.2869744233},
{"learn":[3.617635616],"iteration":671,"passed_time":0.5860646873,"remaining_time":0.2860553831},
{"learn":[3.614434481],"iteration":672,"passed_time":0.5868323778,"remaining_time":0.2851325224},
{"learn":[3.613122476],"iteration":673,"passed_time":0.5876110541,"remaining_time":0.2842154357},
{"learn":[3.611653873],"iteration":674,"passed_time":0.5884189833,"remaining_time":0.2833128438},
{"learn":[3.61157274],"iteration":675,"passed_time":0.589101413,"remaining_time":0.2823503814},
{"learn":[3.610825475],"iteration":676,"passed_time":0.5899294888,"remaining_time":0.2814582347},
{"learn":[3.609627233],"iteration":677,"passed_time":0.5907159076,"remaining_time":0.280546493},
{"learn":[3.607682923],"iteration":678,"passed_time":0.5915051675,"remaining_time":0.2796364636},
{"learn":[3.607518279],"iteration":679,"passed_time":0.5922369934,"remaining_time":0.2786997616},
{"learn":[3.607025005],"iteration":680,"passed_time":0.5932089638,"remaining_time":0.2778761519},
{"learn":[3.605374143],"iteration":681,"passed_time":0.5946125918,"remaining_time":0.2772533786},
{"learn":[3.605220865],"iteration":682,"passed_time":0.5958653837,"remaining_time":0.2765583113},
{"learn":[3.601168453],"iteration":683,"passed_time":0.596724282,"remaining_time":0.2756796391},
{"learn":[3.598449647],"iteration":684,"passed_time":0.5974910515,"remaining_time":0.2747586587},
{"learn":[3.598152227],"iteration":685,"passed_time":0.5982939519,"remaining_time":0.273854666},
{"learn":[3.597016702],"iteration":686,"passed_time":0.599066328,"remaining_time":0.2729370606},
{"learn":[3.593151337],"iteration":687,"passed_time":0.5998388882,"remaining_time":0.2720199609},
{"learn":[3.591557507],"iteration":688,"passed_time":0.6006016506,"remaining_time":0.2710988583},
{"learn":[3.590185231],"iteration":689,"passed_time":0.6013577419,"remaining_time":0.2701752174},
{"learn":[3.58963095],"iteration":690,"passed_time":0.6020972424,"remaining_time":0.2692446424},
{"learn":[3.58746064],"iteration":691,"passed_time":0.6028498361,"remaining_time":0.2683204473},
{"learn":[3.58289274],"iteration":692,"passed_time":0.6036383685,"remaining_time":0.2674126683},
{"learn":[3.580663628],"iteration":693,"passed_time":0.6044497273,"remaining_time":0.2665152976},
{"learn":[3.579261942],"iteration":694,"passed_time":0.605306833,"remaining_time":0.2656382505},
{"learn":[3.575724594],"iteration":695,"passed_time":0.6060979429,"remaining_time":0.2647324348},
{"learn":[3.57563187],"iteration":696,"passed_time":0.6068082239,"remaining_time":0.2637918104},
{"learn":[3.57477365],"iteration":697,"passed_time":0.6077020852,"remaining_time":0.2629312747},
{"learn":[3.57139431],"iteration":698,"passed_time":0.6100923521,"remaining_time":0.2627150186},
{"learn":[3.568737511],"iteration":699,"passed_time":0.6110215152,"remaining_time":0.2618663637},
{"learn":[3.567780799],"iteration":700,"passed_time":0.6117941471,"remaining_time":0.2609507132},
{"learn":[3.566668261],"iteration":701,"passed_time":0.6125550974,"remaining_time":0.2600305114},
{"learn":[3.564596385],"iteration":702,"passed_time":0.6133291138,"remaining_time":0.2591162828},
{"learn":[3.564468579],"iteration":703,"passed_time":0.6140608317,"remaining_time":0.2581846679},
{"learn":[3.563436377],"iteration":704,"passed_time":0.614903794,"remaining_time":0.2573001691},
{"learn":[3.558776709],"iteration":705,"passed_time":0.6157317586,"remaining_time":0.2564095425},
{"learn":[3.556589576],"iteration":706,"passed_time":0.6165614591,"remaining_time":0.2555198126},
{"learn":[3.554764638],"iteration":707,"passed_time":0.61734686,"remaining_time":0.2546119818},
{"learn":[3.553023437],"iteration":708,"passed_time":0.618173345,"remaining_time":0.2537213588},
{"learn":[3.548794661],"iteration":709,"passed_time":0.6189598272,"remaining_time":0.2528145773},
{"learn":[3.546260033],"iteration":710,"passed_time":0.6197818397,"remaining_time":0.2519225762},
{"learn":[3.545076573],"iteration":711,"passed_time":0.6205636708,"remaining_time":0.2510145185},
{"learn":[3.544646208],"iteration":712,"passed_time":0.6212954717,"remaining_time":0.2500866765},
{"learn":[3.541394234],"iteration":713,"passed_time":0.6222240964,"remaining_time":0.2492382235},
{"learn":[3.540561472],"iteration":714,"passed_time":0.6232668405,"remaining_time":0.2484350343},
{"learn":[3.539221531],"iteration":715,"passed_time":0.6246830228,"remaining_time":0.2477792995},
{"learn":[3.538805706],"iteration":716,"passed_time":0.6254633149,"remaining_time":0.2468704576},
{"learn":[3.538278471],"iteration":717,"passed_time":0.6262347509,"remaining_time":0.2459584955},
{"learn":[3.535502627],"iteration":718,"passed_time":0.6269981347,"remaining_time":0.2450437772},
{"learn":[3.534860531],"iteration":719,"passed_time":0.627756552,"remaining_time":0.244127548},
{"learn":[3.532275243],"iteration":720,"passed_time":0.6285290982,"remaining_time":0.2432172239},
{"learn":[3.529733481],"iteration":721,"passed_time":0.6293148123,"remaining_time":0.2423123515},
{"learn":[3.5284647],"iteration":722,"passed_time":0.6300735033,"remaining_time":0.2413974556},
{"learn":[3.526518984],"iteration":723,"passed_time":0.6308796198,"remaining_time":0.2405010705},
{"learn":[3.526329136],"iteration":724,"passed_time":0.6316195714,"remaining_time":0.2395798374},
{"learn":[3.526076622],"iteration":725,"passed_time":0.632369739,"remaining_time":0.2386629593},
{"learn":[3.52464582],"iteration":726,"passed_time":0.6330962107,"remaining_time":0.2377376417},
{"learn":[3.521148749],"iteration":727,"passed_time":0.633918894,"remaining_time":0.2368488176},
{"learn":[3.519187248],"iteration":728,"passed_time":0.6347208289,"remaining_time":0.2359524618},
{"learn":[3.518893131],"iteration":729,"passed_time":0.6362416984,"remaining_time":0.235322272},
{"learn":[3.515093571],"iteration":730,"passed_time":0.6378801457,"remaining_time":0.2347329127},
{"learn":[3.514947599],"iteration":731,"passed_time":0.6390755937,"remaining_time":0.233978496},
{"learn":[3.513990953],"iteration":732,"passed_time":0.6399895043,"remaining_time":0.2331203242},
{"learn":[3.511220205],"iteration":733,"passed_time":0.6408106603,"remaining_time":0.2322283864},
{"learn":[3.510399543],"iteration":734,"passed_time":0.6417361685,"remaining_time":0.2313742648},
{"learn":[3.506816894],"iteration":735,"passed_time":0.6426131816,"remaining_time":0.2305025543},
{"learn":[3.506660102],"iteration":736,"passed_time":0.6433424912,"remaining_time":0.229578121},
{"learn":[3.504906313],"iteration":737,"passed_time":0.644160757,"remaining_time":0.2286857972},
{"learn":[3.50378238],"iteration":738,"passed_time":0.6449559979,"remaining_time":0.2277855419},
{"learn":[3.503312564],"iteration":739,"passed_time":0.6456882421,"remaining_time":0.2268634364},
{"learn":[3.50153114],"iteration":740,"passed_time":0.646484527,"remaining_time":0.2259642274},
{"learn":[3.500543928],"iteration":741,"passed_time":0.6472268324,"remaining_time":0.2250465266},
{"learn":[3.499095401],"iteration":742,"passed_time":0.648061649,"remaining_time":0.2241612972},
{"learn":[3.498744525],"iteration":743,"passed_time":0.6489206547,"remaining_time":0.2232845264},
{"learn":[3.498069556],"iteration":744,"passed_time":0.6497267623,"remaining_time":0.2223896972},
{"learn":[3.497704493],"iteration":745,"passed_time":0.650466007,"remaining_time":0.2214723402},
{"learn":[3.496089579],"iteration":746,"passed_time":0.6513776282,"remaining_time":0.220613842},
{"learn":[3.492613077],"iteration":747,"passed_time":0.6536169766,"remaining_time":0.2202025108},
{"learn":[3.488817785],"iteration":748,"passed_time":0.6545494431,"remaining_time":0.2193483447},
{"learn":[3.48875508],"iteration":749,"passed_time":0.6553540929,"remaining_time":0.2184513643},
{"learn":[3.485711286],"iteration":750,"passed_time":0.6561005511,"remaining_time":0.2175353358},
{"learn":[3.483845476],"iteration":751,"passed_time":0.6568333803,"remaining_time":0.2166152637},
{"learn":[3.48327084],"iteration":752,"passed_time":0.6575394641,"remaining_time":0.2156869159},
{"learn":[3.481835448],"iteration":753,"passed_time":0.6583323316,"remaining_time":0.2147874716},
{"learn":[3.480007393],"iteration":754,"passed_time":0.6591292517,"remaining_time":0.2138896247},
{"learn":[3.478695305],"iteration":755,"passed_time":0.6599107602,"remaining_time":0.2129870708},
{"learn":[3.476628921],"iteration":756,"passed_time":0.6606887079,"remaining_time":0.2120836935},
{"learn":[3.474324897],"iteration":757,"passed_time":0.6614480552,"remaining_time":0.2111747089},
{"learn":[3.47032412],"iteration":758,"passed_time":0.6622733349,"remaining_time":0.2102870536},
{"learn":[3.469072895],"iteration":759,"passed_time":0.6630971184,"remaining_time":0.20939909},
{"learn":[3.468442474],"iteration":760,"passed_time":0.6638577973,"remaining_time":0.2084914764},
{"learn":[3.46638891],"iteration":761,"passed_time":0.6645998225,"remaining_time":0.2075784222},
{"learn":[3.464408328],"iteration":762,"passed_time":0.665376557,"remaining_time":0.2066765977},
{"learn":[3.464084317],"iteration":763,"passed_time":0.6662113435,"remaining_time":0.2057930328},
{"learn":[3.462888715],"iteration":764,"passed_time":0.6675058225,"remaining_time":0.2050508082},
{"learn":[3.461799897],"iteration":765,"passed_time":0.6683310182,"remaining_time":0.2041637836},
{"learn":[3.461166934],"iteration":766,"passed_time":0.6691381515,"remaining_time":0.2032714332},
{"learn":[3.461039813],"iteration":767,"passed_time":0.6698611675,"remaining_time":0.2023538943},
{"learn":[3.460733919],"iteration":768,"passed_time":0.6706386902,"remaining_time":0.2014532346},
{"learn":[3.459248413],"iteration":769,"passed_time":0.6714091712,"remaining_time":0.2005507914},
{"learn":[3.454830857],"iteration":770,"passed_time":0.672271502,"remaining_time":0.1996759714},
{"learn":[3.454028925],"iteration":771,"passed_time":0.673116812,"remaining_time":0.1987961569},
{"learn":[3.452216873],"iteration":772,"passed_time":0.6738729912,"remaining_time":0.1978902574},
{"learn":[3.450422099],"iteration":773,"passed_time":0.6746681948,"remaining_time":0.1969961396},
{"learn":[3.449826879],"iteration":774,"passed_time":0.6755054097,"remaining_time":0.1961144738},
{"learn":[3.449316119],"iteration":775,"passed_time":0.676204582,"remaining_time":0.1951930752},
{"learn":[3.44920895],"iteration":776,"passed_time":0.6770830201,"remaining_time":0.1943236982},
{"learn":[3.448883485],"iteration":777,"passed_time":0.6778324746,"remaining_time":0.1934174928},
{"learn":[3.447290874],"iteration":778,"passed_time":0.6786561285,"remaining_time":0.1925327399},
{"learn":[3.444091523],"iteration":779,"passed_time":0.6794577981,"remaining_time":0.1916419431},
{"learn":[3.442728702],"iteration":780,"passed_time":0.680255701,"remaining_time":0.1907503182},
{"learn":[3.440110197],"iteration":781,"passed_time":0.6810019417,"remaining_time":0.1898445311},
{"learn":[3.435612663],"iteration":782,"passed_time":0.6830268043,"remaining_time":0.1892935077},
{"learn":[3.433946037],"iteration":783,"passed_time":0.6839521473,"remaining_time":0.1884357957},
{"learn":[3.432226891],"iteration":784,"passed_time":0.6847383592,"remaining_time":0.1875398054},
{"learn":[3.429411587],"iteration":785,"passed_time":0.6855387467,"remaining_time":0.1866479539},
{"learn":[3.429009365],"iteration":786,"passed_time":0.6863863845,"remaining_time":0.1857691231},
{"learn":[3.428652453],"iteration":787,"passed_time":0.6872574395,"remaining_time":0.1848966715},
{"learn":[3.426346144],"iteration":788,"passed_time":0.6880907359,"remaining_time":0.1840141258},
{"learn":[3.424416006],"iteration":789,"passed_time":0.688909365,"remaining_time":0.1831278059},
{"learn":[3.421070872],"iteration":790,"passed_time":0.6897383012,"remaining_time":0.1822443805},
{"learn":[3.420910284],"iteration":791,"passed_time":0.690533699,"remaining_time":0.1813522846},
{"learn":[3.418801374],"iteration":792,"passed_time":0.6912612976,"remaining_time":0.1804427347},
{"learn":[3.417667413],"iteration":793,"passed_time":0.6921296522,"remaining_time":0.1795701616},
{"learn":[3.415153494],"iteration":794,"passed_time":0.6928879065,"remaining_time":0.1786692086},
{"learn":[3.413485828],"iteration":795,"passed_time":0.6936998371,"remaining_time":0.1777823703},
{"learn":[3.412560596],"iteration":796,"passed_time":0.694515817,"remaining_time":0.1768967514},
{"learn":[3.408908001],"iteration":797,"passed_time":0.6952730195,"remaining_time":0.1759964285},
{"learn":[3.407357664],"iteration":798,"passed_time":0.6960901574,"remaining_time":0.1751115415},
{"learn":[3.405901313],"iteration":799,"passed_time":0.6983481545,"remaining_time":0.1745870386},
{"learn":[3.40534627],"iteration":800,"passed_time":0.6996698095,"remaining_time":0.1738255831},
{"learn":[3.403262364],"iteration":801,"passed_time":0.7007577904,"remaining_time":0.1730050405},
{"learn":[3.401928057],"iteration":802,"passed_time":0.7015210813,"remaining_time":0.1721041756},
{"learn":[3.399318863],"iteration":803,"passed_time":0.7022244251,"remaining_time":0.171189039},
{"learn":[3.398645776],"iteration":804,"passed_time":0.7029638422,"remaining_time":0.1702831667},
{"learn":[3.398040764],"iteration":805,"passed_time":0.7037599953,"remaining_time":0.1693913636},
{"learn":[3.396909506],"iteration":806,"passed_time":0.7044959038,"remaining_time":0.1684853896},
{"learn":[3.39538724],"iteration":807,"passed_time":0.7052850975,"remaining_time":0.1675924984},
{"learn":[3.394479911],"iteration":808,"passed_time":0.7061218786,"remaining_time":0.1667110986},
{"learn":[3.392286385],"iteration":809,"passed_time":0.7068600214,"remaining_time":0.1658066717},
{"learn":[3.390918815],"iteration":810,"passed_time":0.7076117958,"remaining_time":0.1649058316},
{"learn":[3.38891516],"iteration":811,"passed_time":0.7083518882,"remaining_time":0.1640026539},
{"learn":[3.386582017],"iteration":812,"passed_time":0.7091350147,"remaining_time":0.1631097758},
{"learn":[3.385358565],"iteration":813,"passed_time":0.7098952659,"remaining_time":0.1622119404},
{"learn":[3.38316013],"iteration":814,"passed_time":0.7107291886,"remaining_time":0.1613311655},
{"learn":[3.379825821],"iteration":815,"passed_time":0.7121391691,"remaining_time":0.1605804009},
{"learn":[3.377130404],"iteration":816,"passed_time":0.712982652,"remaining_time":0.1597011326},
{"learn":[3.376311726],"iteration":817,"passed_time":0.7137179565,"remaining_time":0.1587978827},
{"learn":[3.374794695],"iteration":818,"passed_time":0.7146362239,"remaining_time":0.1579354781},
{"learn":[3.373225901],"iteration":819,"passed_time":0.7156943356,"remaining_time":0.1571036346},
{"learn":[3.3707259],"iteration":820,"passed_time":0.7165802353,"remaining_time":0.1562336932},
{"learn":[3.368657434],"iteration":821,"passed_time":0.717359593,"remaining_time":0.1553406418},
{"learn":[3.366189542],"iteration":822,"passed_time":0.7181555636,"remaining_time":0.1544514396},
{"learn":[3.364395223],"iteration":823,"passed_time":0.7188676328,"remaining_time":0.1535445429},
{"learn":[3.360961815],"iteration":824,"passed_time":0.7196603284,"remaining_time":0.1526552212},
{"learn":[3.359850955],"iteration":825,"passed_time":0.720405846,"remaining_time":0.1517561952},
{"learn":[3.358746321],"iteration":826,"passed_time":0.7211599394,"remaining_time":0.1508593344},
{"learn":[3.357429623],"iteration":827,"passed_time":0.7219129041,"remaining_time":0.149962584},
{"learn":[3.356194078],"iteration":828,"passed_time":0.7232740213,"remaining_time":0.1491916256},
{"learn":[3.354301202],"iteration":829,"passed_time":0.7243285021,"remaining_time":0.1483564402},
{"learn":[3.351131271],"iteration":830,"passed_time":0.7251578599,"remaining_time":0.1474749438},
{"learn":[3.350340536],"iteration":831,"passed_time":0.7264734272,"remaining_time":0.1466917497},
{"learn":[3.349711334],"iteration":832,"passed_time":0.7277903788,"remaining_time":0.1459075549},
{"learn":[3.346613267],"iteration":833,"passed_time":0.7287965641,"remaining_time":0.1450602274},
{"learn":[3.345303866],"iteration":834,"passed_time":0.7296224484,"remaining_time":0.144176891},
{"learn":[3.345188623],"iteration":835,"passed_time":0.7303797461,"remaining_time":0.1432802373},
{"learn":[3.343949141],"iteration":836,"passed_time":0.7311481986,"remaining_time":0.1423860889},
{"learn":[3.343847438],"iteration":837,"passed_time":0.7319247257,"remaining_time":0.1414938014},
{"learn":[3.343778941],"iteration":838,"passed_time":0.7327259286,"remaining_time":0.140606525},
{"learn":[3.343684703],"iteration":839,"passed_time":0.7335126778,"remaining_time":0.1397167005},
{"learn":[3.340519785],"iteration":840,"passed_time":0.7342663562,"remaining_time":0.1388208688},
{"learn":[3.338253239],"iteration":841,"passed_time":0.7349615993,"remaining_time":0.1379144094},
{"learn":[3.337157588],"iteration":842,"passed_time":0.7358207747,"remaining_time":0.1370389818},
{"learn":[3.337041406],"iteration":843,"passed_time":0.7367251785,"remaining_time":0.1361719524},
{"learn":[3.336227786],"iteration":844,"passed_time":0.7375869069,"remaining_time":0.1352970066},
{"learn":[3.332540946],"iteration":845,"passed_time":0.7384104818,"remaining_time":0.1344151468},
{"learn":[3.331746517],"iteration":846,"passed_time":0.739179416,"remaining_time":0.1335235545},
{"learn":[3.330251688],"iteration":847,"passed_time":0.7399375603,"remaining_time":0.1326303174},
{"learn":[3.32764006],"iteration":848,"passed_time":0.741143351,"remaining_time":0.1318170153},
{"learn":[3.325464518],"iteration":849,"passed_time":0.742244795,"remaining_time":0.1309843756},
{"learn":[3.322839852],"iteration":850,"passed_time":0.7431150018,"remaining_time":0.1301106172},
{"learn":[3.321195989],"iteration":851,"passed_time":0.7439643366,"remaining_time":0.1292332416},
{"learn":[3.32015077],"iteration":852,"passed_time":0.7446890396,"remaining_time":0.1283344535},
{"learn":[3.320103066],"iteration":853,"passed_time":0.7453900641,"remaining_time":0.127432025},
{"learn":[3.319004188],"iteration":854,"passed_time":0.7461618956,"remaining_time":0.1265420759},
{"learn":[3.318641756],"iteration":855,"passed_time":0.7469931274,"remaining_time":0.1256623953},
{"learn":[3.317718195],"iteration":856,"passed_time":0.7477873042,"remaining_time":0.1247766447},
{"learn":[3.316442476],"iteration":857,"passed_time":0.7486220173,"remaining_time":0.1238978164},
{"learn":[3.314725435],"iteration":858,"passed_time":0.7494496815,"remaining_time":0.1230179338},
{"learn":[3.31218951],"iteration":859,"passed_time":0.7502227678,"remaining_time":0.1221292878},
{"learn":[3.30935234],"iteration":860,"passed_time":0.7509895812,"remaining_time":0.1212398975},
{"learn":[3.306850347],"iteration":861,"passed_time":0.7518048508,"remaining_time":0.1203585492},
{"learn":[3.306637117],"iteration":862,"passed_time":0.7526800161,"remaining_time":0.1194868624},
{"learn":[3.304407121],"iteration":863,"passed_time":0.7534705525,"remaining_time":0.1186018462},
{"learn":[3.303012722],"iteration":864,"passed_time":0.7542619316,"remaining_time":0.1177171801},
{"learn":[3.30031376],"iteration":865,"passed_time":0.7551378718,"remaining_time":0.1168458139},
{"learn":[3.298523169],"iteration":866,"passed_time":0.7573975231,"remaining_time":0.1161867019},
{"learn":[3.29454864],"iteration":867,"passed_time":0.7582253286,"remaining_time":0.115306156},
{"learn":[3.292154428],"iteration":868,"passed_time":0.7590796159,"remaining_time":0.1144297235},
{"learn":[3.288847694],"iteration":869,"passed_time":0.7600291798,"remaining_time":0.1135675786},
{"learn":[3.284670405],"iteration":870,"passed_time":0.7609727322,"remaining_time":0.1127043427},
{"learn":[3.281910713],"iteration":871,"passed_time":0.7617935544,"remaining_time":0.1118229071},
{"learn":[3.278965041],"iteration":872,"passed_time":0.7626488257,"remaining_time":0.1109466218},
{"learn":[3.277665266],"iteration":873,"passed_time":0.7634885269,"remaining_time":0.11006814},
{"learn":[3.276132071],"iteration":874,"passed_time":0.7643111997,"remaining_time":0.1091873142},
{"learn":[3.274681973],"iteration":875,"passed_time":0.765073318,"remaining_time":0.1082980496},
{"learn":[3.27363594],"iteration":876,"passed_time":0.7658187038,"remaining_time":0.1074067281},
{"learn":[3.27355374],"iteration":877,"passed_time":0.7665857147,"remaining_time":0.106518744},
{"learn":[3.270660116],"iteration":878,"passed_time":0.7675875114,"remaining_time":0.1056633548},
{"learn":[3.269613773],"iteration":879,"passed_time":0.7685243848,"remaining_time":0.1047987797},
{"learn":[3.268226465],"iteration":880,"passed_time":0.7693398952,"remaining_time":0.1039176476},
{"learn":[3.266914857],"iteration":881,"passed_time":0.7707268162,"remaining_time":0.1031131115},
{"learn":[3.265400133],"iteration":882,"passed_time":0.7720455032,"remaining_time":0.102298215},
{"learn":[3.262289019],"iteration":883,"passed_time":0.7729525057,"remaining_time":0.1014281569},
{"learn":[3.261580392],"iteration":884,"passed_time":0.7737811166,"remaining_time":0.1005478287},
{"learn":[3.260982414],"iteration":885,"passed_time":0.7745204803,"remaining_time":0.09965613403},
{"learn":[3.259514539],"iteration":886,"passed_time":0.7753822581,"remaining_time":0.09878037787},
{"learn":[3.258640173],"iteration":887,"passed_time":0.7761829627,"remaining_time":0.09789695025},
{"learn":[3.25625749],"iteration":888,"passed_time":0.7770672422,"remaining_time":0.09702414385},
{"learn":[3.253365934],"iteration":889,"passed_time":0.7778633997,"remaining_time":0.09614042018},
{"learn":[3.253282131],"iteration":890,"passed_time":0.7786166336,"remaining_time":0.09525164205},
{"learn":[3.251620331],"iteration":891,"passed_time":0.7794328805,"remaining_time":0.09437079719},
{"learn":[3.249082405],"iteration":892,"passed_time":0.780253018,"remaining_time":0.09349056318},
{"learn":[3.246022694],"iteration":893,"passed_time":0.7810510483,"remaining_time":0.09260784241},
{"learn":[3.244782512],"iteration":894,"passed_time":0.7818531383,"remaining_time":0.09172578718},
{"learn":[3.242315702],"iteration":895,"passed_time":0.7826349989,"remaining_time":0.09084156238},
{"learn":[3.240054595],"iteration":896,"passed_time":0.7834443988,"remaining_time":0.08996072806},
{"learn":[3.239112293],"iteration":897,"passed_time":0.7843730274,"remaining_time":0.08909359554},
{"learn":[3.238148522],"iteration":898,"passed_time":0.7869442471,"remaining_time":0.08841086647},
{"learn":[3.235469812],"iteration":899,"passed_time":0.7880605125,"remaining_time":0.08756227917},
{"learn":[3.235126871],"iteration":900,"passed_time":0.788819965,"remaining_time":0.08667389182},
{"learn":[3.234752862],"iteration":901,"passed_time":0.7895666946,"remaining_time":0.08578440806},
{"learn":[3.234014968],"iteration":902,"passed_time":0.7902700068,"remaining_time":0.08489057658},
{"learn":[3.233113365],"iteration":903,"passed_time":0.7910139103,"remaining_time":0.08400147719},
{"learn":[3.231902322],"iteration":904,"passed_time":0.7918496128,"remaining_time":0.08312233505},
{"learn":[3.231862166],"iteration":905,"passed_time":0.7924623985,"remaining_time":0.08222016055},
{"learn":[3.228710504],"iteration":906,"passed_time":0.7932264742,"remaining_time":0.08133413683},
{"learn":[3.224414862],"iteration":907,"passed_time":0.7940592289,"remaining_time":0.08045534037},
{"learn":[3.224231704],"iteration":908,"passed_time":0.7948291754,"remaining_time":0.07957035749},
{"learn":[3.221142848],"iteration":909,"passed_time":0.7956507218,"remaining_time":0.07869073073},
{"learn":[3.219768627],"iteration":910,"passed_time":0.7964731537,"remaining_time":0.07781131798},
{"learn":[3.218366676],"iteration":911,"passed_time":0.7972394587,"remaining_time":0.07692661444},
{"learn":[3.216962539],"iteration":912,"passed_time":0.7980292843,"remaining_time":0.07604441154},
{"learn":[3.215732704],"iteration":913,"passed_time":0.7988489724,"remaining_time":0.0751652206},
{"learn":[3.211623277],"iteration":914,"passed_time":0.8008489817,"remaining_time":0.07439580704},
{"learn":[3.208786544],"iteration":915,"passed_time":0.8021231149,"remaining_time":0.07355714154},
{"learn":[3.207486543],"iteration":916,"passed_time":0.8032985631,"remaining_time":0.07270859405},
{"learn":[3.20474656],"iteration":917,"passed_time":0.8042828509,"remaining_time":0.07184225901},
{"learn":[3.20250212],"iteration":918,"passed_time":0.8051412002,"remaining_time":0.07096456716},
{"learn":[3.201145721],"iteration":919,"passed_time":0.8060119037,"remaining_time":0.07008799162},
{"learn":[3.199927405],"iteration":920,"passed_time":0.8067406365,"remaining_time":0.06919925112},
{"learn":[3.198672703],"iteration":921,"passed_time":0.8075042744,"remaining_time":0.06831381063},
{"learn":[3.197603549],"iteration":922,"passed_time":0.8082970885,"remaining_time":0.06743106806},
{"learn":[3.195158362],"iteration":923,"passed_time":0.8091901005,"remaining_time":0.06655676152},
{"learn":[3.191358455],"iteration":924,"passed_time":0.8099874661,"remaining_time":0.06567465942},
{"learn":[3.190803721],"iteration":925,"passed_time":0.8107829156,"remaining_time":0.06479258721},
{"learn":[3.189750662],"iteration":926,"passed_time":0.8115444727,"remaining_time":0.06390803291},
{"learn":[3.188724584],"iteration":927,"passed_time":0.8123284292,"remaining_time":0.06302548157},
{"learn":[3.187434836],"iteration":928,"passed_time":0.8131025923,"remaining_time":0.06214239403},
{"learn":[3.186055316],"iteration":929,"passed_time":0.8151773194,"remaining_time":0.06135743264},
{"learn":[3.18300603],"iteration":930,"passed_time":0.8166343383,"remaining_time":0.06052391981},
{"learn":[3.181858465],"iteration":931,"passed_time":0.8175510679,"remaining_time":0.05964964873},
{"learn":[3.181089554],"iteration":932,"passed_time":0.8183406153,"remaining_time":0.05876615351},
{"learn":[3.18101367],"iteration":933,"passed_time":0.8191704449,"remaining_time":0.05788570595},
{"learn":[3.178313946],"iteration":934,"passed_time":0.8200245281,"remaining_time":0.05700705276},
{"learn":[3.1775891],"iteration":935,"passed_time":0.8209352132,"remaining_time":0.05613232227},
{"learn":[3.177463672],"iteration":936,"passed_time":0.8216601009,"remaining_time":0.05524502279},
{"learn":[3.174075472],"iteration":937,"passed_time":0.8224264576,"remaining_time":0.05436081063},
{"learn":[3.172202209],"iteration":938,"passed_time":0.823271652,"remaining_time":0.053481971},
{"learn":[3.169468986],"iteration":939,"passed_time":0.8240769498,"remaining_time":0.05260065637},
{"learn":[3.168288745],"iteration":940,"passed_time":0.8248098898,"remaining_time":0.05171496652},
{"learn":[3.167836246],"iteration":941,"passed_time":0.8255150458,"remaining_time":0.05082789029},
{"learn":[3.166247734],"iteration":942,"passed_time":0.8263325057,"remaining_time":0.04994798815},
{"learn":[3.165116311],"iteration":943,"passed_time":0.8271155215,"remaining_time":0.04906617501},
{"learn":[3.163181623],"iteration":944,"passed_time":0.8278998656,"remaining_time":0.04818464826},
{"learn":[3.162364353],"iteration":945,"passed_time":0.8297390136,"remaining_time":0.04736353778},
{"learn":[3.161575301],"iteration":946,"passed_time":0.8313370843,"remaining_time":0.04652678508},
{"learn":[3.161497115],"iteration":947,"passed_time":0.8322351345,"remaining_time":0.04565002848},
{"learn":[3.159912557],"iteration":948,"passed_time":0.8330474745,"remaining_time":0.04476862086},
{"learn":[3.157538244],"iteration":949,"passed_time":0.8338749324,"remaining_time":0.04388815433},
{"learn":[3.156812591],"iteration":950,"passed_time":0.8347772526,"remaining_time":0.04301165655},
{"learn":[3.155972323],"iteration":951,"passed_time":0.8355333122,"remaining_time":0.04212773002},
{"learn":[3.154882758],"iteration":952,"passed_time":0.8362785572,"remaining_time":0.0412435385},
{"learn":[3.154842851],"iteration":953,"passed_time":0.8370560299,"remaining_time":0.04036119222},
{"learn":[3.153553378],"iteration":954,"passed_time":0.8382037331,"remaining_time":0.03949651098},
{"learn":[3.15111659],"iteration":955,"passed_time":0.8390623911,"remaining_time":0.03861793432},
{"learn":[3.150545594],"iteration":956,"passed_time":0.8398874395,"remaining_time":0.03773788913},
{"learn":[3.148738072],"iteration":957,"passed_time":0.8406575718,"remaining_time":0.03685555116},
{"learn":[3.147443718],"iteration":958,"passed_time":0.8414225018,"remaining_time":0.03597322479},
{"learn":[3.145021556],"iteration":959,"passed_time":0.8422750382,"remaining_time":0.03509479326},
{"learn":[3.144436576],"iteration":960,"passed_time":0.8434130026,"remaining_time":0.03422799907},
{"learn":[3.143532321],"iteration":961,"passed_time":0.8449781639,"remaining_time":0.03337751583},
{"learn":[3.142364253],"iteration":962,"passed_time":0.8459697152,"remaining_time":0.03250350931},
{"learn":[3.141537559],"iteration":963,"passed_time":0.8467720556,"remaining_time":0.03162219295},
{"learn":[3.140397905],"iteration":964,"passed_time":0.847540453,"remaining_time":0.03073980918},
{"learn":[3.13867693],"iteration":965,"passed_time":0.8483762724,"remaining_time":0.02986003443},
{"learn":[3.137177945],"iteration":966,"passed_time":0.8492353104,"remaining_time":0.02898114296},
{"learn":[3.136967467],"iteration":967,"passed_time":0.8499754617,"remaining_time":0.02809836237},
{"learn":[3.136504585],"iteration":968,"passed_time":0.8507409863,"remaining_time":0.0272166879},
{"learn":[3.133953852],"iteration":969,"passed_time":0.8515469732,"remaining_time":0.02633650433},
{"learn":[3.131955523],"iteration":970,"passed_time":0.8523427247,"remaining_time":0.02545616788},
{"learn":[3.131483871],"iteration":971,"passed_time":0.8531421316,"remaining_time":0.02457611079},
{"learn":[3.129069456],"iteration":972,"passed_time":0.8539368346,"remaining_time":0.02369608894},
{"learn":[3.128147177],"iteration":973,"passed_time":0.8547192553,"remaining_time":0.02281591441},
{"learn":[3.126895395],"iteration":974,"passed_time":0.8554982898,"remaining_time":0.02193585358},
{"learn":[3.124742852],"iteration":975,"passed_time":0.8562912802,"remaining_time":0.02105634296},
{"learn":[3.122117211],"iteration":976,"passed_time":0.8572582958,"remaining_time":0.02018110625},
{"learn":[3.120582433],"iteration":977,"passed_time":0.859339722,"remaining_time":0.01933075039},
{"learn":[3.120499074],"iteration":978,"passed_time":0.860480032,"remaining_time":0.01845769221},
{"learn":[3.117356269],"iteration":979,"passed_time":0.8614849758,"remaining_time":0.01758132604},
{"learn":[3.116348841],"iteration":980,"passed_time":0.8622579854,"remaining_time":0.01670020563},
{"learn":[3.116253174],"iteration":981,"passed_time":0.8629924227,"remaining_time":0.01581859838},
{"learn":[3.115118065],"iteration":982,"passed_time":0.8638181552,"remaining_time":0.01493886942},
{"learn":[3.113728381],"iteration":983,"passed_time":0.8645650199,"remaining_time":0.0140579678},
{"learn":[3.110468887],"iteration":984,"passed_time":0.865346138,"remaining_time":0.01317785997},
{"learn":[3.10772785],"iteration":985,"passed_time":0.8661033917,"remaining_time":0.01229761408},
{"learn":[3.107501937],"iteration":986,"passed_time":0.8668335262,"remaining_time":0.01141726022},
{"learn":[3.104832371],"iteration":987,"passed_time":0.8676366241,"remaining_time":0.01053809665},
{"learn":[3.103656252],"iteration":988,"passed_time":0.8684692175,"remaining_time":0.009659414957},
{"learn":[3.102693763],"iteration":989,"passed_time":0.8692535148,"remaining_time":0.008780338534},
{"learn":[3.102615402],"iteration":990,"passed_time":0.8699674662,"remaining_time":0.007900814527},
{"learn":[3.10072795],"iteration":991,"passed_time":0.8708040688,"remaining_time":0.007022613458},
{"learn":[3.099541153],"iteration":992,"passed_time":0.8715995655,"remaining_time":0.006144206404},
{"learn":[3.099392561],"iteration":993,"passed_time":0.8726885649,"remaining_time":0.005267737816},
{"learn":[3.098084333],"iteration":994,"passed_time":0.8744639997,"remaining_time":0.004394291456},
{"learn":[3.097648553],"iteration":995,"passed_time":0.8753146923,"remaining_time":0.003515320049},
{"learn":[3.097362845],"iteration":996,"passed_time":0.8761636544,"remaining_time":0.002636400164},
{"learn":[3.096533678],"iteration":997,"passed_time":0.8769602486,"remaining_time":0.001757435368},
{"learn":[3.096037475],"iteration":998,"passed_time":0.8777096764,"remaining_time":0.0008785882646},
{"learn":[3.095433912],"iteration":999,"passed_time":0.878496786,"remaining_time":0}
]}